[{"Team_ID": 1610612746, "Game_ID": "0021401216", "GAME_DATE": "APR 14, 2015", "MATCHUP": "LAC @ PHX", "WL": "W", "MIN": 240, "FGM": 42, "FGA": 87, "FG_PCT": 0.483, "FG3M": 15, "FG3A": 38, "FG3_PCT": 0.39473684210526316, "FTM": 13, "FTA": 18, "FT_PCT": 0.722, "OREB": 11, "DREB": 33, "REB": 44, "AST": 26, "STL": 10, "BLK": 5, "TOV": 12, "PF": 19, "PTS": 112}, {"Team_ID": 1610612746, "Game_ID": "0021401213", "GAME_DATE": "APR 13, 2015", "MATCHUP": "LAC vs. DEN", "WL": "W", "MIN": 240, "FGM": 37, "FGA": 82, "FG_PCT": 0.451, "FG3M": 7, "FG3A": 21, "FG3_PCT": 0.3333333333333333, "FTM": 29, "FTA": 37, "FT_PCT": 0.784, "OREB": 13, "DREB": 34, "REB": 47, "AST": 25, "STL": 7, "BLK": 8, "TOV": 13, "PF": 16, "PTS": 110}, {"Team_ID": 1610612746, "Game_ID": "0021401190", "GAME_DATE": "APR 11, 2015", "MATCHUP": "LAC vs. MEM", "WL": "W", "MIN": 240, "FGM": 35, "FGA": 88, "FG_PCT": 0.398, "FG3M": 6, "FG3A": 27, "FG3_PCT": 0.2222222222222222, "FTM": 18, "FTA": 22, "FT_PCT": 0.818, "OREB": 12, "DREB": 31, "REB": 43, "AST": 25, "STL": 10, "BLK": 6, "TOV": 13, "PF": 21, "PTS": 94}, {"Team_ID": 1610612746, "Game_ID": "0021401159", "GAME_DATE": "APR 07, 2015", "MATCHUP": "LAC vs. LAL", "WL": "W", "MIN": 240, "FGM": 39, "FGA": 81, "FG_PCT": 0.481, "FG3M": 7, "FG3A": 24, "FG3_PCT": 0.2916666666666667, "FTM": 20, "FTA": 30, "FT_PCT": 0.667, "OREB": 6, "DREB": 40, "REB": 46, "AST": 25, "STL": 6, "BLK": 6, "TOV": 8, "PF": 22, "PTS": 105}, {"Team_ID": 1610612746, "Game_ID": "0021401153", "GAME_DATE": "APR 05, 2015", "MATCHUP": "LAC @ LAL", "WL": "W", "MIN": 240, "FGM": 40, "FGA": 75, "FG_PCT": 0.533, "FG3M": 15, "FG3A": 27, "FG3_PCT": 0.5555555555555556, "FTM": 11, "FTA": 18, "FT_PCT": 0.611, "OREB": 7, "DREB": 33, "REB": 40, "AST": 27, "STL": 10, "BLK": 1, "TOV": 10, "PF": 20, "PTS": 106}, {"Team_ID": 1610612746, "Game_ID": "0021401144", "GAME_DATE": "APR 04, 2015", "MATCHUP": "LAC @ DEN", "WL": "W", "MIN": 240, "FGM": 34, "FGA": 79, "FG_PCT": 0.43, "FG3M": 13, "FG3A": 34, "FG3_PCT": 0.38235294117647056, "FTM": 26, "FTA": 42, "FT_PCT": 0.619, "OREB": 13, "DREB": 34, "REB": 47, "AST": 24, "STL": 9, "BLK": 7, "TOV": 12, "PF": 27, "PTS": 107}, {"Team_ID": 1610612746, "Game_ID": "0021401122", "GAME_DATE": "APR 01, 2015", "MATCHUP": "LAC @ POR", "WL": "W", "MIN": 240, "FGM": 46, "FGA": 86, "FG_PCT": 0.535, "FG3M": 15, "FG3A": 28, "FG3_PCT": 0.5357142857142857, "FTM": 19, "FTA": 24, "FT_PCT": 0.792, "OREB": 7, "DREB": 33, "REB": 40, "AST": 30, "STL": 6, "BLK": 3, "TOV": 6, "PF": 21, "PTS": 126}, {"Team_ID": 1610612746, "Game_ID": "0021401111", "GAME_DATE": "MAR 31, 2015", "MATCHUP": "LAC vs. GSW", "WL": "L", "MIN": 240, "FGM": 36, "FGA": 82, "FG_PCT": 0.439, "FG3M": 6, "FG3A": 22, "FG3_PCT": 0.2727272727272727, "FTM": 28, "FTA": 33, "FT_PCT": 0.848, "OREB": 10, "DREB": 31, "REB": 41, "AST": 19, "STL": 4, "BLK": 8, "TOV": 11, "PF": 24, "PTS": 106}, {"Team_ID": 1610612746, "Game_ID": "0021401095", "GAME_DATE": "MAR 29, 2015", "MATCHUP": "LAC @ BOS", "WL": "W", "MIN": 240, "FGM": 41, "FGA": 84, "FG_PCT": 0.488, "FG3M": 13, "FG3A": 32, "FG3_PCT": 0.40625, "FTM": 24, "FTA": 40, "FT_PCT": 0.6, "OREB": 13, "DREB": 40, "REB": 53, "AST": 28, "STL": 5, "BLK": 5, "TOV": 12, "PF": 21, "PTS": 119}, {"Team_ID": 1610612746, "Game_ID": "0021401075", "GAME_DATE": "MAR 27, 2015", "MATCHUP": "LAC @ PHI", "WL": "W", "MIN": 240, "FGM": 44, "FGA": 82, "FG_PCT": 0.537, "FG3M": 12, "FG3A": 29, "FG3_PCT": 0.41379310344827586, "FTM": 19, "FTA": 31, "FT_PCT": 0.613, "OREB": 8, "DREB": 48, "REB": 56, "AST": 28, "STL": 8, "BLK": 2, "TOV": 16, "PF": 24, "PTS": 119}, {"Team_ID": 1610612746, "Game_ID": "0021401061", "GAME_DATE": "MAR 25, 2015", "MATCHUP": "LAC @ NYK", "WL": "W", "MIN": 240, "FGM": 44, "FGA": 78, "FG_PCT": 0.564, "FG3M": 11, "FG3A": 28, "FG3_PCT": 0.39285714285714285, "FTM": 12, "FTA": 18, "FT_PCT": 0.667, "OREB": 6, "DREB": 33, "REB": 39, "AST": 31, "STL": 12, "BLK": 7, "TOV": 15, "PF": 17, "PTS": 111}, {"Team_ID": 1610612746, "Game_ID": "0021401040", "GAME_DATE": "MAR 22, 2015", "MATCHUP": "LAC vs. NOP", "WL": "W", "MIN": 240, "FGM": 42, "FGA": 91, "FG_PCT": 0.462, "FG3M": 7, "FG3A": 23, "FG3_PCT": 0.30434782608695654, "FTM": 16, "FTA": 23, "FT_PCT": 0.696, "OREB": 16, "DREB": 26, "REB": 42, "AST": 25, "STL": 10, "BLK": 7, "TOV": 10, "PF": 17, "PTS": 107}, {"Team_ID": 1610612746, "Game_ID": "0021401031", "GAME_DATE": "MAR 20, 2015", "MATCHUP": "LAC vs. WAS", "WL": "W", "MIN": 240, "FGM": 45, "FGA": 86, "FG_PCT": 0.523, "FG3M": 12, "FG3A": 23, "FG3_PCT": 0.5217391304347826, "FTM": 11, "FTA": 17, "FT_PCT": 0.647, "OREB": 8, "DREB": 38, "REB": 46, "AST": 33, "STL": 5, "BLK": 6, "TOV": 14, "PF": 21, "PTS": 113}, {"Team_ID": 1610612746, "Game_ID": "0021401013", "GAME_DATE": "MAR 18, 2015", "MATCHUP": "LAC @ SAC", "WL": "W", "MIN": 240, "FGM": 45, "FGA": 88, "FG_PCT": 0.511, "FG3M": 17, "FG3A": 37, "FG3_PCT": 0.4594594594594595, "FTM": 9, "FTA": 13, "FT_PCT": 0.692, "OREB": 8, "DREB": 28, "REB": 36, "AST": 27, "STL": 5, "BLK": 6, "TOV": 11, "PF": 23, "PTS": 116}, {"Team_ID": 1610612746, "Game_ID": "0021401004", "GAME_DATE": "MAR 17, 2015", "MATCHUP": "LAC vs. CHA", "WL": "W", "MIN": 240, "FGM": 35, "FGA": 77, "FG_PCT": 0.455, "FG3M": 9, "FG3A": 24, "FG3_PCT": 0.375, "FTM": 20, "FTA": 28, "FT_PCT": 0.714, "OREB": 7, "DREB": 37, "REB": 44, "AST": 24, "STL": 7, "BLK": 4, "TOV": 12, "PF": 26, "PTS": 99}, {"Team_ID": 1610612746, "Game_ID": "0021400983", "GAME_DATE": "MAR 15, 2015", "MATCHUP": "LAC vs. HOU", "WL": "L", "MIN": 240, "FGM": 36, "FGA": 82, "FG_PCT": 0.439, "FG3M": 12, "FG3A": 26, "FG3_PCT": 0.46153846153846156, "FTM": 14, "FTA": 24, "FT_PCT": 0.583, "OREB": 8, "DREB": 42, "REB": 50, "AST": 24, "STL": 8, "BLK": 8, "TOV": 20, "PF": 30, "PTS": 98}, {"Team_ID": 1610612746, "Game_ID": "0021400972", "GAME_DATE": "MAR 13, 2015", "MATCHUP": "LAC @ DAL", "WL": "L", "MIN": 240, "FGM": 41, "FGA": 82, "FG_PCT": 0.5, "FG3M": 12, "FG3A": 32, "FG3_PCT": 0.375, "FTM": 5, "FTA": 12, "FT_PCT": 0.417, "OREB": 11, "DREB": 21, "REB": 32, "AST": 27, "STL": 9, "BLK": 2, "TOV": 15, "PF": 17, "PTS": 99}, {"Team_ID": 1610612746, "Game_ID": "0021400957", "GAME_DATE": "MAR 11, 2015", "MATCHUP": "LAC @ OKC", "WL": "W", "MIN": 240, "FGM": 35, "FGA": 76, "FG_PCT": 0.461, "FG3M": 15, "FG3A": 30, "FG3_PCT": 0.5, "FTM": 35, "FTA": 47, "FT_PCT": 0.745, "OREB": 11, "DREB": 27, "REB": 38, "AST": 22, "STL": 11, "BLK": 2, "TOV": 12, "PF": 27, "PTS": 120}, {"Team_ID": 1610612746, "Game_ID": "0021400945", "GAME_DATE": "MAR 09, 2015", "MATCHUP": "LAC vs. MIN", "WL": "W", "MIN": 240, "FGM": 35, "FGA": 79, "FG_PCT": 0.443, "FG3M": 11, "FG3A": 31, "FG3_PCT": 0.3548387096774194, "FTM": 8, "FTA": 15, "FT_PCT": 0.533, "OREB": 9, "DREB": 33, "REB": 42, "AST": 30, "STL": 11, "BLK": 2, "TOV": 15, "PF": 23, "PTS": 89}, {"Team_ID": 1610612746, "Game_ID": "0021400932", "GAME_DATE": "MAR 08, 2015", "MATCHUP": "LAC @ GSW", "WL": "L", "MIN": 240, "FGM": 40, "FGA": 83, "FG_PCT": 0.482, "FG3M": 8, "FG3A": 25, "FG3_PCT": 0.32, "FTM": 10, "FTA": 14, "FT_PCT": 0.714, "OREB": 9, "DREB": 30, "REB": 39, "AST": 25, "STL": 8, "BLK": 3, "TOV": 18, "PF": 22, "PTS": 98}, {"Team_ID": 1610612746, "Game_ID": "0021400908", "GAME_DATE": "MAR 04, 2015", "MATCHUP": "LAC vs. POR", "WL": "L", "MIN": 265, "FGM": 37, "FGA": 96, "FG_PCT": 0.385, "FG3M": 11, "FG3A": 31, "FG3_PCT": 0.3548387096774194, "FTM": 8, "FTA": 18, "FT_PCT": 0.444, "OREB": 9, "DREB": 42, "REB": 51, "AST": 25, "STL": 6, "BLK": 4, "TOV": 9, "PF": 26, "PTS": 93}, {"Team_ID": 1610612746, "Game_ID": "0021400888", "GAME_DATE": "MAR 02, 2015", "MATCHUP": "LAC @ MIN", "WL": "W", "MIN": 240, "FGM": 44, "FGA": 92, "FG_PCT": 0.478, "FG3M": 12, "FG3A": 33, "FG3_PCT": 0.36363636363636365, "FTM": 10, "FTA": 19, "FT_PCT": 0.526, "OREB": 9, "DREB": 34, "REB": 43, "AST": 24, "STL": 7, "BLK": 3, "TOV": 11, "PF": 26, "PTS": 110}, {"Team_ID": 1610612746, "Game_ID": "0021400877", "GAME_DATE": "MAR 01, 2015", "MATCHUP": "LAC @ CHI", "WL": "W", "MIN": 240, "FGM": 38, "FGA": 87, "FG_PCT": 0.437, "FG3M": 7, "FG3A": 27, "FG3_PCT": 0.25925925925925924, "FTM": 13, "FTA": 24, "FT_PCT": 0.542, "OREB": 13, "DREB": 42, "REB": 55, "AST": 15, "STL": 6, "BLK": 12, "TOV": 8, "PF": 23, "PTS": 96}, {"Team_ID": 1610612746, "Game_ID": "0021400864", "GAME_DATE": "FEB 27, 2015", "MATCHUP": "LAC @ MEM", "WL": "W", "MIN": 240, "FGM": 36, "FGA": 78, "FG_PCT": 0.462, "FG3M": 9, "FG3A": 26, "FG3_PCT": 0.34615384615384615, "FTM": 16, "FTA": 28, "FT_PCT": 0.571, "OREB": 9, "DREB": 38, "REB": 47, "AST": 20, "STL": 9, "BLK": 10, "TOV": 11, "PF": 19, "PTS": 97}, {"Team_ID": 1610612746, "Game_ID": "0021400846", "GAME_DATE": "FEB 25, 2015", "MATCHUP": "LAC @ HOU", "WL": "L", "MIN": 240, "FGM": 40, "FGA": 91, "FG_PCT": 0.44, "FG3M": 11, "FG3A": 32, "FG3_PCT": 0.34375, "FTM": 14, "FTA": 19, "FT_PCT": 0.737, "OREB": 12, "DREB": 37, "REB": 49, "AST": 18, "STL": 1, "BLK": 4, "TOV": 15, "PF": 22, "PTS": 105}, {"Team_ID": 1610612746, "Game_ID": "0021400837", "GAME_DATE": "FEB 23, 2015", "MATCHUP": "LAC vs. MEM", "WL": "L", "MIN": 240, "FGM": 35, "FGA": 79, "FG_PCT": 0.443, "FG3M": 9, "FG3A": 27, "FG3_PCT": 0.3333333333333333, "FTM": 8, "FTA": 12, "FT_PCT": 0.667, "OREB": 5, "DREB": 35, "REB": 40, "AST": 21, "STL": 6, "BLK": 10, "TOV": 13, "PF": 16, "PTS": 87}, {"Team_ID": 1610612746, "Game_ID": "0021400820", "GAME_DATE": "FEB 21, 2015", "MATCHUP": "LAC vs. SAC", "WL": "W", "MIN": 240, "FGM": 46, "FGA": 95, "FG_PCT": 0.484, "FG3M": 14, "FG3A": 35, "FG3_PCT": 0.4, "FTM": 20, "FTA": 28, "FT_PCT": 0.714, "OREB": 11, "DREB": 43, "REB": 54, "AST": 31, "STL": 9, "BLK": 11, "TOV": 11, "PF": 29, "PTS": 126}, {"Team_ID": 1610612746, "Game_ID": "0021400802", "GAME_DATE": "FEB 19, 2015", "MATCHUP": "LAC vs. SAS", "WL": "W", "MIN": 240, "FGM": 42, "FGA": 77, "FG_PCT": 0.545, "FG3M": 8, "FG3A": 19, "FG3_PCT": 0.42105263157894735, "FTM": 27, "FTA": 52, "FT_PCT": 0.519, "OREB": 10, "DREB": 33, "REB": 43, "AST": 26, "STL": 10, "BLK": 4, "TOV": 12, "PF": 22, "PTS": 119}, {"Team_ID": 1610612746, "Game_ID": "0021400799", "GAME_DATE": "FEB 11, 2015", "MATCHUP": "LAC vs. HOU", "WL": "W", "MIN": 240, "FGM": 39, "FGA": 81, "FG_PCT": 0.481, "FG3M": 4, "FG3A": 22, "FG3_PCT": 0.18181818181818182, "FTM": 28, "FTA": 45, "FT_PCT": 0.622, "OREB": 12, "DREB": 37, "REB": 49, "AST": 25, "STL": 13, "BLK": 3, "TOV": 15, "PF": 24, "PTS": 110}, {"Team_ID": 1610612746, "Game_ID": "0021400781", "GAME_DATE": "FEB 09, 2015", "MATCHUP": "LAC @ DAL", "WL": "W", "MIN": 240, "FGM": 41, "FGA": 92, "FG_PCT": 0.446, "FG3M": 9, "FG3A": 27, "FG3_PCT": 0.3333333333333333, "FTM": 24, "FTA": 29, "FT_PCT": 0.828, "OREB": 17, "DREB": 36, "REB": 53, "AST": 21, "STL": 8, "BLK": 3, "TOV": 6, "PF": 25, "PTS": 115}, {"Team_ID": 1610612746, "Game_ID": "0021400765", "GAME_DATE": "FEB 08, 2015", "MATCHUP": "LAC @ OKC", "WL": "L", "MIN": 240, "FGM": 42, "FGA": 90, "FG_PCT": 0.467, "FG3M": 12, "FG3A": 32, "FG3_PCT": 0.375, "FTM": 12, "FTA": 17, "FT_PCT": 0.706, "OREB": 8, "DREB": 21, "REB": 29, "AST": 28, "STL": 9, "BLK": 2, "TOV": 13, "PF": 26, "PTS": 108}, {"Team_ID": 1610612746, "Game_ID": "0021400752", "GAME_DATE": "FEB 06, 2015", "MATCHUP": "LAC @ TOR", "WL": "L", "MIN": 240, "FGM": 38, "FGA": 78, "FG_PCT": 0.487, "FG3M": 6, "FG3A": 23, "FG3_PCT": 0.2608695652173913, "FTM": 25, "FTA": 31, "FT_PCT": 0.806, "OREB": 7, "DREB": 23, "REB": 30, "AST": 21, "STL": 8, "BLK": 4, "TOV": 8, "PF": 21, "PTS": 107}, {"Team_ID": 1610612746, "Game_ID": "0021400743", "GAME_DATE": "FEB 05, 2015", "MATCHUP": "LAC @ CLE", "WL": "L", "MIN": 240, "FGM": 38, "FGA": 91, "FG_PCT": 0.418, "FG3M": 5, "FG3A": 22, "FG3_PCT": 0.22727272727272727, "FTM": 13, "FTA": 20, "FT_PCT": 0.65, "OREB": 14, "DREB": 29, "REB": 43, "AST": 24, "STL": 9, "BLK": 1, "TOV": 12, "PF": 29, "PTS": 94}, {"Team_ID": 1610612746, "Game_ID": "0021400720", "GAME_DATE": "FEB 02, 2015", "MATCHUP": "LAC @ BKN", "WL": "L", "MIN": 240, "FGM": 42, "FGA": 89, "FG_PCT": 0.472, "FG3M": 8, "FG3A": 23, "FG3_PCT": 0.34782608695652173, "FTM": 8, "FTA": 25, "FT_PCT": 0.32, "OREB": 15, "DREB": 37, "REB": 52, "AST": 23, "STL": 6, "BLK": 1, "TOV": 12, "PF": 22, "PTS": 100}, {"Team_ID": 1610612746, "Game_ID": "0021400714", "GAME_DATE": "JAN 31, 2015", "MATCHUP": "LAC @ SAS", "WL": "W", "MIN": 240, "FGM": 40, "FGA": 91, "FG_PCT": 0.44, "FG3M": 8, "FG3A": 22, "FG3_PCT": 0.36363636363636365, "FTM": 17, "FTA": 18, "FT_PCT": 0.944, "OREB": 16, "DREB": 40, "REB": 56, "AST": 20, "STL": 12, "BLK": 7, "TOV": 15, "PF": 23, "PTS": 105}, {"Team_ID": 1610612746, "Game_ID": "0021400701", "GAME_DATE": "JAN 30, 2015", "MATCHUP": "LAC @ NOP", "WL": "L", "MIN": 240, "FGM": 42, "FGA": 92, "FG_PCT": 0.457, "FG3M": 7, "FG3A": 28, "FG3_PCT": 0.25, "FTM": 12, "FTA": 17, "FT_PCT": 0.706, "OREB": 9, "DREB": 29, "REB": 38, "AST": 20, "STL": 5, "BLK": 4, "TOV": 5, "PF": 21, "PTS": 103}, {"Team_ID": 1610612746, "Game_ID": "0021400690", "GAME_DATE": "JAN 28, 2015", "MATCHUP": "LAC @ UTA", "WL": "W", "MIN": 240, "FGM": 34, "FGA": 76, "FG_PCT": 0.447, "FG3M": 9, "FG3A": 26, "FG3_PCT": 0.34615384615384615, "FTM": 17, "FTA": 25, "FT_PCT": 0.68, "OREB": 10, "DREB": 27, "REB": 37, "AST": 13, "STL": 7, "BLK": 6, "TOV": 8, "PF": 20, "PTS": 94}, {"Team_ID": 1610612746, "Game_ID": "0021400674", "GAME_DATE": "JAN 26, 2015", "MATCHUP": "LAC vs. DEN", "WL": "W", "MIN": 240, "FGM": 38, "FGA": 80, "FG_PCT": 0.475, "FG3M": 7, "FG3A": 19, "FG3_PCT": 0.3684210526315789, "FTM": 19, "FTA": 22, "FT_PCT": 0.864, "OREB": 10, "DREB": 35, "REB": 45, "AST": 25, "STL": 10, "BLK": 8, "TOV": 13, "PF": 17, "PTS": 102}, {"Team_ID": 1610612746, "Game_ID": "0021400659", "GAME_DATE": "JAN 25, 2015", "MATCHUP": "LAC @ PHX", "WL": "W", "MIN": 240, "FGM": 43, "FGA": 87, "FG_PCT": 0.494, "FG3M": 10, "FG3A": 23, "FG3_PCT": 0.43478260869565216, "FTM": 24, "FTA": 36, "FT_PCT": 0.667, "OREB": 14, "DREB": 36, "REB": 50, "AST": 28, "STL": 7, "BLK": 5, "TOV": 11, "PF": 20, "PTS": 120}, {"Team_ID": 1610612746, "Game_ID": "0021400640", "GAME_DATE": "JAN 22, 2015", "MATCHUP": "LAC vs. BKN", "WL": "W", "MIN": 240, "FGM": 49, "FGA": 83, "FG_PCT": 0.59, "FG3M": 11, "FG3A": 25, "FG3_PCT": 0.44, "FTM": 14, "FTA": 21, "FT_PCT": 0.667, "OREB": 9, "DREB": 39, "REB": 48, "AST": 41, "STL": 8, "BLK": 9, "TOV": 14, "PF": 17, "PTS": 123}, {"Team_ID": 1610612746, "Game_ID": "0021400614", "GAME_DATE": "JAN 19, 2015", "MATCHUP": "LAC vs. BOS", "WL": "W", "MIN": 240, "FGM": 39, "FGA": 82, "FG_PCT": 0.476, "FG3M": 9, "FG3A": 21, "FG3_PCT": 0.42857142857142855, "FTM": 15, "FTA": 19, "FT_PCT": 0.789, "OREB": 10, "DREB": 34, "REB": 44, "AST": 27, "STL": 6, "BLK": 10, "TOV": 11, "PF": 14, "PTS": 102}, {"Team_ID": 1610612746, "Game_ID": "0021400607", "GAME_DATE": "JAN 17, 2015", "MATCHUP": "LAC @ SAC", "WL": "W", "MIN": 240, "FGM": 44, "FGA": 92, "FG_PCT": 0.478, "FG3M": 9, "FG3A": 28, "FG3_PCT": 0.32142857142857145, "FTM": 20, "FTA": 31, "FT_PCT": 0.645, "OREB": 11, "DREB": 23, "REB": 34, "AST": 24, "STL": 7, "BLK": 6, "TOV": 5, "PF": 22, "PTS": 117}, {"Team_ID": 1610612746, "Game_ID": "0021400599", "GAME_DATE": "JAN 16, 2015", "MATCHUP": "LAC vs. CLE", "WL": "L", "MIN": 240, "FGM": 43, "FGA": 91, "FG_PCT": 0.473, "FG3M": 10, "FG3A": 29, "FG3_PCT": 0.3448275862068966, "FTM": 25, "FTA": 36, "FT_PCT": 0.694, "OREB": 17, "DREB": 26, "REB": 43, "AST": 26, "STL": 9, "BLK": 1, "TOV": 13, "PF": 21, "PTS": 121}, {"Team_ID": 1610612746, "Game_ID": "0021400583", "GAME_DATE": "JAN 14, 2015", "MATCHUP": "LAC @ POR", "WL": "W", "MIN": 240, "FGM": 37, "FGA": 88, "FG_PCT": 0.42, "FG3M": 8, "FG3A": 23, "FG3_PCT": 0.34782608695652173, "FTM": 18, "FTA": 19, "FT_PCT": 0.947, "OREB": 7, "DREB": 37, "REB": 44, "AST": 20, "STL": 9, "BLK": 2, "TOV": 7, "PF": 22, "PTS": 100}, {"Team_ID": 1610612746, "Game_ID": "0021400559", "GAME_DATE": "JAN 11, 2015", "MATCHUP": "LAC vs. MIA", "WL": "L", "MIN": 240, "FGM": 34, "FGA": 75, "FG_PCT": 0.453, "FG3M": 9, "FG3A": 26, "FG3_PCT": 0.34615384615384615, "FTM": 13, "FTA": 18, "FT_PCT": 0.722, "OREB": 6, "DREB": 21, "REB": 27, "AST": 17, "STL": 4, "BLK": 2, "TOV": 13, "PF": 24, "PTS": 90}, {"Team_ID": 1610612746, "Game_ID": "0021400550", "GAME_DATE": "JAN 10, 2015", "MATCHUP": "LAC vs. DAL", "WL": "W", "MIN": 240, "FGM": 46, "FGA": 88, "FG_PCT": 0.523, "FG3M": 13, "FG3A": 31, "FG3_PCT": 0.41935483870967744, "FTM": 15, "FTA": 21, "FT_PCT": 0.714, "OREB": 9, "DREB": 38, "REB": 47, "AST": 31, "STL": 8, "BLK": 5, "TOV": 10, "PF": 17, "PTS": 120}, {"Team_ID": 1610612746, "Game_ID": "0021400534", "GAME_DATE": "JAN 07, 2015", "MATCHUP": "LAC vs. LAL", "WL": "W", "MIN": 240, "FGM": 40, "FGA": 85, "FG_PCT": 0.471, "FG3M": 12, "FG3A": 33, "FG3_PCT": 0.36363636363636365, "FTM": 22, "FTA": 30, "FT_PCT": 0.733, "OREB": 8, "DREB": 34, "REB": 42, "AST": 29, "STL": 9, "BLK": 5, "TOV": 6, "PF": 16, "PTS": 114}, {"Team_ID": 1610612746, "Game_ID": "0021400519", "GAME_DATE": "JAN 05, 2015", "MATCHUP": "LAC vs. ATL", "WL": "L", "MIN": 240, "FGM": 33, "FGA": 74, "FG_PCT": 0.446, "FG3M": 7, "FG3A": 25, "FG3_PCT": 0.28, "FTM": 25, "FTA": 33, "FT_PCT": 0.758, "OREB": 8, "DREB": 37, "REB": 45, "AST": 23, "STL": 5, "BLK": 5, "TOV": 21, "PF": 25, "PTS": 98}, {"Team_ID": 1610612746, "Game_ID": "0021400502", "GAME_DATE": "JAN 03, 2015", "MATCHUP": "LAC vs. PHI", "WL": "W", "MIN": 240, "FGM": 46, "FGA": 85, "FG_PCT": 0.541, "FG3M": 15, "FG3A": 37, "FG3_PCT": 0.40540540540540543, "FTM": 20, "FTA": 26, "FT_PCT": 0.769, "OREB": 9, "DREB": 34, "REB": 43, "AST": 33, "STL": 13, "BLK": 3, "TOV": 8, "PF": 19, "PTS": 127}, {"Team_ID": 1610612746, "Game_ID": "0021400477", "GAME_DATE": "DEC 31, 2014", "MATCHUP": "LAC vs. NYK", "WL": "W", "MIN": 240, "FGM": 36, "FGA": 82, "FG_PCT": 0.439, "FG3M": 15, "FG3A": 34, "FG3_PCT": 0.4411764705882353, "FTM": 12, "FTA": 20, "FT_PCT": 0.6, "OREB": 5, "DREB": 45, "REB": 50, "AST": 28, "STL": 6, "BLK": 3, "TOV": 10, "PF": 13, "PTS": 99}, {"Team_ID": 1610612746, "Game_ID": "0021400464", "GAME_DATE": "DEC 29, 2014", "MATCHUP": "LAC vs. UTA", "WL": "W", "MIN": 240, "FGM": 37, "FGA": 81, "FG_PCT": 0.457, "FG3M": 10, "FG3A": 23, "FG3_PCT": 0.43478260869565216, "FTM": 17, "FTA": 22, "FT_PCT": 0.773, "OREB": 7, "DREB": 34, "REB": 41, "AST": 24, "STL": 7, "BLK": 12, "TOV": 14, "PF": 16, "PTS": 101}, {"Team_ID": 1610612746, "Game_ID": "0021400443", "GAME_DATE": "DEC 27, 2014", "MATCHUP": "LAC vs. TOR", "WL": "L", "MIN": 240, "FGM": 37, "FGA": 81, "FG_PCT": 0.457, "FG3M": 12, "FG3A": 25, "FG3_PCT": 0.48, "FTM": 12, "FTA": 15, "FT_PCT": 0.8, "OREB": 9, "DREB": 34, "REB": 43, "AST": 26, "STL": 4, "BLK": 7, "TOV": 14, "PF": 19, "PTS": 98}, {"Team_ID": 1610612746, "Game_ID": "0021400431", "GAME_DATE": "DEC 25, 2014", "MATCHUP": "LAC vs. GSW", "WL": "W", "MIN": 240, "FGM": 34, "FGA": 87, "FG_PCT": 0.391, "FG3M": 9, "FG3A": 32, "FG3_PCT": 0.28125, "FTM": 23, "FTA": 31, "FT_PCT": 0.742, "OREB": 11, "DREB": 39, "REB": 50, "AST": 18, "STL": 10, "BLK": 4, "TOV": 13, "PF": 20, "PTS": 100}, {"Team_ID": 1610612746, "Game_ID": "0021400420", "GAME_DATE": "DEC 23, 2014", "MATCHUP": "LAC @ ATL", "WL": "L", "MIN": 240, "FGM": 37, "FGA": 92, "FG_PCT": 0.402, "FG3M": 11, "FG3A": 29, "FG3_PCT": 0.3793103448275862, "FTM": 19, "FTA": 28, "FT_PCT": 0.679, "OREB": 16, "DREB": 35, "REB": 51, "AST": 26, "STL": 10, "BLK": 5, "TOV": 10, "PF": 23, "PTS": 104}, {"Team_ID": 1610612746, "Game_ID": "0021400414", "GAME_DATE": "DEC 22, 2014", "MATCHUP": "LAC @ SAS", "WL": "L", "MIN": 240, "FGM": 43, "FGA": 86, "FG_PCT": 0.5, "FG3M": 10, "FG3A": 24, "FG3_PCT": 0.4166666666666667, "FTM": 22, "FTA": 29, "FT_PCT": 0.759, "OREB": 11, "DREB": 25, "REB": 36, "AST": 23, "STL": 10, "BLK": 5, "TOV": 10, "PF": 22, "PTS": 118}, {"Team_ID": 1610612746, "Game_ID": "0021400399", "GAME_DATE": "DEC 20, 2014", "MATCHUP": "LAC vs. MIL", "WL": "W", "MIN": 240, "FGM": 37, "FGA": 81, "FG_PCT": 0.457, "FG3M": 12, "FG3A": 26, "FG3_PCT": 0.46153846153846156, "FTM": 20, "FTA": 27, "FT_PCT": 0.741, "OREB": 11, "DREB": 30, "REB": 41, "AST": 29, "STL": 10, "BLK": 4, "TOV": 12, "PF": 18, "PTS": 106}, {"Team_ID": 1610612746, "Game_ID": "0021400391", "GAME_DATE": "DEC 19, 2014", "MATCHUP": "LAC @ DEN", "WL": "L", "MIN": 240, "FGM": 39, "FGA": 85, "FG_PCT": 0.459, "FG3M": 3, "FG3A": 18, "FG3_PCT": 0.16666666666666666, "FTM": 25, "FTA": 33, "FT_PCT": 0.758, "OREB": 13, "DREB": 26, "REB": 39, "AST": 21, "STL": 14, "BLK": 4, "TOV": 11, "PF": 22, "PTS": 106}, {"Team_ID": 1610612746, "Game_ID": "0021400377", "GAME_DATE": "DEC 17, 2014", "MATCHUP": "LAC vs. IND", "WL": "W", "MIN": 240, "FGM": 34, "FGA": 78, "FG_PCT": 0.436, "FG3M": 6, "FG3A": 18, "FG3_PCT": 0.3333333333333333, "FTM": 28, "FTA": 45, "FT_PCT": 0.622, "OREB": 14, "DREB": 37, "REB": 51, "AST": 20, "STL": 7, "BLK": 4, "TOV": 12, "PF": 15, "PTS": 102}, {"Team_ID": 1610612746, "Game_ID": "0021400362", "GAME_DATE": "DEC 15, 2014", "MATCHUP": "LAC vs. DET", "WL": "W", "MIN": 240, "FGM": 43, "FGA": 80, "FG_PCT": 0.538, "FG3M": 12, "FG3A": 24, "FG3_PCT": 0.5, "FTM": 15, "FTA": 20, "FT_PCT": 0.75, "OREB": 12, "DREB": 29, "REB": 41, "AST": 35, "STL": 9, "BLK": 3, "TOV": 14, "PF": 21, "PTS": 113}, {"Team_ID": 1610612746, "Game_ID": "0021400344", "GAME_DATE": "DEC 13, 2014", "MATCHUP": "LAC @ MIL", "WL": "L", "MIN": 240, "FGM": 39, "FGA": 91, "FG_PCT": 0.429, "FG3M": 14, "FG3A": 29, "FG3_PCT": 0.4827586206896552, "FTM": 14, "FTA": 19, "FT_PCT": 0.737, "OREB": 10, "DREB": 25, "REB": 35, "AST": 24, "STL": 8, "BLK": 3, "TOV": 12, "PF": 24, "PTS": 106}, {"Team_ID": 1610612746, "Game_ID": "0021400329", "GAME_DATE": "DEC 12, 2014", "MATCHUP": "LAC @ WAS", "WL": "L", "MIN": 240, "FGM": 32, "FGA": 75, "FG_PCT": 0.427, "FG3M": 6, "FG3A": 20, "FG3_PCT": 0.3, "FTM": 26, "FTA": 31, "FT_PCT": 0.839, "OREB": 12, "DREB": 25, "REB": 37, "AST": 14, "STL": 7, "BLK": 2, "TOV": 18, "PF": 20, "PTS": 96}, {"Team_ID": 1610612746, "Game_ID": "0021400317", "GAME_DATE": "DEC 10, 2014", "MATCHUP": "LAC @ IND", "WL": "W", "MIN": 240, "FGM": 42, "FGA": 88, "FG_PCT": 0.477, "FG3M": 7, "FG3A": 24, "FG3_PCT": 0.2916666666666667, "FTM": 12, "FTA": 14, "FT_PCT": 0.857, "OREB": 10, "DREB": 40, "REB": 50, "AST": 25, "STL": 7, "BLK": 7, "TOV": 12, "PF": 17, "PTS": 103}, {"Team_ID": 1610612746, "Game_ID": "0021400307", "GAME_DATE": "DEC 08, 2014", "MATCHUP": "LAC vs. PHX", "WL": "W", "MIN": 265, "FGM": 44, "FGA": 96, "FG_PCT": 0.458, "FG3M": 9, "FG3A": 31, "FG3_PCT": 0.2903225806451613, "FTM": 24, "FTA": 30, "FT_PCT": 0.8, "OREB": 10, "DREB": 35, "REB": 45, "AST": 27, "STL": 7, "BLK": 5, "TOV": 11, "PF": 22, "PTS": 121}, {"Team_ID": 1610612746, "Game_ID": "0021400293", "GAME_DATE": "DEC 06, 2014", "MATCHUP": "LAC vs. NOP", "WL": "W", "MIN": 240, "FGM": 43, "FGA": 78, "FG_PCT": 0.551, "FG3M": 17, "FG3A": 32, "FG3_PCT": 0.53125, "FTM": 17, "FTA": 24, "FT_PCT": 0.708, "OREB": 6, "DREB": 32, "REB": 38, "AST": 34, "STL": 7, "BLK": 6, "TOV": 7, "PF": 20, "PTS": 120}, {"Team_ID": 1610612746, "Game_ID": "0021400272", "GAME_DATE": "DEC 03, 2014", "MATCHUP": "LAC vs. ORL", "WL": "W", "MIN": 240, "FGM": 42, "FGA": 78, "FG_PCT": 0.538, "FG3M": 12, "FG3A": 31, "FG3_PCT": 0.3870967741935484, "FTM": 18, "FTA": 25, "FT_PCT": 0.72, "OREB": 6, "DREB": 38, "REB": 44, "AST": 32, "STL": 11, "BLK": 6, "TOV": 17, "PF": 17, "PTS": 114}, {"Team_ID": 1610612746, "Game_ID": "0021400252", "GAME_DATE": "DEC 01, 2014", "MATCHUP": "LAC vs. MIN", "WL": "W", "MIN": 240, "FGM": 41, "FGA": 80, "FG_PCT": 0.513, "FG3M": 15, "FG3A": 34, "FG3_PCT": 0.4411764705882353, "FTM": 30, "FTA": 36, "FT_PCT": 0.833, "OREB": 9, "DREB": 41, "REB": 50, "AST": 33, "STL": 5, "BLK": 7, "TOV": 14, "PF": 26, "PTS": 127}, {"Team_ID": 1610612746, "Game_ID": "0021400239", "GAME_DATE": "NOV 29, 2014", "MATCHUP": "LAC @ UTA", "WL": "W", "MIN": 240, "FGM": 45, "FGA": 80, "FG_PCT": 0.563, "FG3M": 11, "FG3A": 28, "FG3_PCT": 0.39285714285714285, "FTM": 11, "FTA": 15, "FT_PCT": 0.733, "OREB": 9, "DREB": 28, "REB": 37, "AST": 21, "STL": 6, "BLK": 5, "TOV": 11, "PF": 25, "PTS": 112}, {"Team_ID": 1610612746, "Game_ID": "0021400228", "GAME_DATE": "NOV 28, 2014", "MATCHUP": "LAC @ HOU", "WL": "W", "MIN": 240, "FGM": 38, "FGA": 81, "FG_PCT": 0.469, "FG3M": 9, "FG3A": 25, "FG3_PCT": 0.36, "FTM": 17, "FTA": 22, "FT_PCT": 0.773, "OREB": 8, "DREB": 37, "REB": 45, "AST": 23, "STL": 8, "BLK": 4, "TOV": 10, "PF": 18, "PTS": 102}, {"Team_ID": 1610612746, "Game_ID": "0021400216", "GAME_DATE": "NOV 26, 2014", "MATCHUP": "LAC @ DET", "WL": "W", "MIN": 240, "FGM": 37, "FGA": 78, "FG_PCT": 0.474, "FG3M": 12, "FG3A": 28, "FG3_PCT": 0.42857142857142855, "FTM": 18, "FTA": 19, "FT_PCT": 0.947, "OREB": 9, "DREB": 30, "REB": 39, "AST": 21, "STL": 9, "BLK": 3, "TOV": 15, "PF": 19, "PTS": 104}, {"Team_ID": 1610612746, "Game_ID": "0021400198", "GAME_DATE": "NOV 24, 2014", "MATCHUP": "LAC @ CHA", "WL": "W", "MIN": 240, "FGM": 45, "FGA": 88, "FG_PCT": 0.511, "FG3M": 15, "FG3A": 32, "FG3_PCT": 0.46875, "FTM": 8, "FTA": 10, "FT_PCT": 0.8, "OREB": 8, "DREB": 35, "REB": 43, "AST": 28, "STL": 2, "BLK": 2, "TOV": 8, "PF": 24, "PTS": 113}, {"Team_ID": 1610612746, "Game_ID": "0021400193", "GAME_DATE": "NOV 23, 2014", "MATCHUP": "LAC @ MEM", "WL": "L", "MIN": 240, "FGM": 32, "FGA": 77, "FG_PCT": 0.416, "FG3M": 7, "FG3A": 25, "FG3_PCT": 0.28, "FTM": 20, "FTA": 28, "FT_PCT": 0.714, "OREB": 5, "DREB": 27, "REB": 32, "AST": 14, "STL": 10, "BLK": 1, "TOV": 10, "PF": 27, "PTS": 91}, {"Team_ID": 1610612746, "Game_ID": "0021400170", "GAME_DATE": "NOV 20, 2014", "MATCHUP": "LAC @ MIA", "WL": "W", "MIN": 240, "FGM": 43, "FGA": 77, "FG_PCT": 0.558, "FG3M": 13, "FG3A": 31, "FG3_PCT": 0.41935483870967744, "FTM": 11, "FTA": 17, "FT_PCT": 0.647, "OREB": 4, "DREB": 31, "REB": 35, "AST": 31, "STL": 6, "BLK": 0, "TOV": 13, "PF": 21, "PTS": 110}, {"Team_ID": 1610612746, "Game_ID": "0021400161", "GAME_DATE": "NOV 19, 2014", "MATCHUP": "LAC @ ORL", "WL": "W", "MIN": 240, "FGM": 45, "FGA": 84, "FG_PCT": 0.536, "FG3M": 12, "FG3A": 21, "FG3_PCT": 0.5714285714285714, "FTM": 12, "FTA": 16, "FT_PCT": 0.75, "OREB": 2, "DREB": 37, "REB": 39, "AST": 24, "STL": 8, "BLK": 9, "TOV": 7, "PF": 19, "PTS": 114}, {"Team_ID": 1610612746, "Game_ID": "0021400154", "GAME_DATE": "NOV 17, 2014", "MATCHUP": "LAC vs. CHI", "WL": "L", "MIN": 240, "FGM": 36, "FGA": 81, "FG_PCT": 0.444, "FG3M": 7, "FG3A": 23, "FG3_PCT": 0.30434782608695654, "FTM": 10, "FTA": 22, "FT_PCT": 0.455, "OREB": 9, "DREB": 31, "REB": 40, "AST": 20, "STL": 2, "BLK": 5, "TOV": 12, "PF": 21, "PTS": 89}, {"Team_ID": 1610612746, "Game_ID": "0021400141", "GAME_DATE": "NOV 15, 2014", "MATCHUP": "LAC vs. PHX", "WL": "W", "MIN": 240, "FGM": 36, "FGA": 68, "FG_PCT": 0.529, "FG3M": 14, "FG3A": 29, "FG3_PCT": 0.4827586206896552, "FTM": 34, "FTA": 43, "FT_PCT": 0.791, "OREB": 4, "DREB": 43, "REB": 47, "AST": 24, "STL": 5, "BLK": 12, "TOV": 20, "PF": 26, "PTS": 120}, {"Team_ID": 1610612746, "Game_ID": "0021400102", "GAME_DATE": "NOV 10, 2014", "MATCHUP": "LAC vs. SAS", "WL": "L", "MIN": 240, "FGM": 33, "FGA": 74, "FG_PCT": 0.446, "FG3M": 5, "FG3A": 22, "FG3_PCT": 0.22727272727272727, "FTM": 14, "FTA": 17, "FT_PCT": 0.824, "OREB": 8, "DREB": 36, "REB": 44, "AST": 26, "STL": 6, "BLK": 8, "TOV": 15, "PF": 20, "PTS": 85}, {"Team_ID": 1610612746, "Game_ID": "0021400082", "GAME_DATE": "NOV 08, 2014", "MATCHUP": "LAC vs. POR", "WL": "W", "MIN": 240, "FGM": 40, "FGA": 81, "FG_PCT": 0.494, "FG3M": 5, "FG3A": 12, "FG3_PCT": 0.4166666666666667, "FTM": 21, "FTA": 30, "FT_PCT": 0.7, "OREB": 8, "DREB": 29, "REB": 37, "AST": 17, "STL": 8, "BLK": 4, "TOV": 7, "PF": 19, "PTS": 106}, {"Team_ID": 1610612746, "Game_ID": "0021400068", "GAME_DATE": "NOV 05, 2014", "MATCHUP": "LAC @ GSW", "WL": "L", "MIN": 240, "FGM": 38, "FGA": 82, "FG_PCT": 0.463, "FG3M": 7, "FG3A": 19, "FG3_PCT": 0.3684210526315789, "FTM": 21, "FTA": 27, "FT_PCT": 0.778, "OREB": 5, "DREB": 25, "REB": 30, "AST": 26, "STL": 12, "BLK": 2, "TOV": 14, "PF": 14, "PTS": 104}, {"Team_ID": 1610612746, "Game_ID": "0021400048", "GAME_DATE": "NOV 03, 2014", "MATCHUP": "LAC vs. UTA", "WL": "W", "MIN": 240, "FGM": 41, "FGA": 81, "FG_PCT": 0.506, "FG3M": 10, "FG3A": 23, "FG3_PCT": 0.43478260869565216, "FTM": 15, "FTA": 17, "FT_PCT": 0.882, "OREB": 5, "DREB": 30, "REB": 35, "AST": 28, "STL": 6, "BLK": 6, "TOV": 10, "PF": 17, "PTS": 107}, {"Team_ID": 1610612746, "Game_ID": "0021400039", "GAME_DATE": "NOV 02, 2014", "MATCHUP": "LAC vs. SAC", "WL": "L", "MIN": 240, "FGM": 33, "FGA": 88, "FG_PCT": 0.375, "FG3M": 9, "FG3A": 31, "FG3_PCT": 0.2903225806451613, "FTM": 17, "FTA": 21, "FT_PCT": 0.81, "OREB": 11, "DREB": 24, "REB": 35, "AST": 23, "STL": 10, "BLK": 7, "TOV": 8, "PF": 25, "PTS": 92}, {"Team_ID": 1610612746, "Game_ID": "0021400026", "GAME_DATE": "OCT 31, 2014", "MATCHUP": "LAC @ LAL", "WL": "W", "MIN": 240, "FGM": 34, "FGA": 71, "FG_PCT": 0.479, "FG3M": 12, "FG3A": 33, "FG3_PCT": 0.36363636363636365, "FTM": 38, "FTA": 44, "FT_PCT": 0.864, "OREB": 6, "DREB": 30, "REB": 36, "AST": 25, "STL": 6, "BLK": 2, "TOV": 14, "PF": 26, "PTS": 118}, {"Team_ID": 1610612746, "Game_ID": "0021400020", "GAME_DATE": "OCT 30, 2014", "MATCHUP": "LAC vs. OKC", "WL": "W", "MIN": 240, "FGM": 34, "FGA": 87, "FG_PCT": 0.391, "FG3M": 7, "FG3A": 30, "FG3_PCT": 0.23333333333333334, "FTM": 18, "FTA": 25, "FT_PCT": 0.72, "OREB": 14, "DREB": 19, "REB": 33, "AST": 17, "STL": 10, "BLK": 4, "TOV": 11, "PF": 27, "PTS": 93}]