[{"Team_ID": 1610612760, "Game_ID": "0021601225", "GAME_DATE": "APR 12, 2017", "MATCHUP": "OKC vs. DEN", "WL": "L", "MIN": 240, "FGM": 43, "FGA": 101, "FG_PCT": 0.426, "FG3M": 8, "FG3A": 25, "FG3_PCT": 0.32, "FTM": 11, "FTA": 17, "FT_PCT": 0.647, "OREB": 14, "DREB": 37, "REB": 51, "AST": 20, "STL": 10, "BLK": 8, "TOV": 12, "PF": 24, "PTS": 105}, {"Team_ID": 1610612760, "Game_ID": "0021601213", "GAME_DATE": "APR 11, 2017", "MATCHUP": "OKC @ MIN", "WL": "W", "MIN": 240, "FGM": 37, "FGA": 86, "FG_PCT": 0.43, "FG3M": 7, "FG3A": 22, "FG3_PCT": 0.3181818181818182, "FTM": 19, "FTA": 25, "FT_PCT": 0.76, "OREB": 18, "DREB": 36, "REB": 54, "AST": 22, "STL": 7, "BLK": 4, "TOV": 17, "PF": 21, "PTS": 100}, {"Team_ID": 1610612760, "Game_ID": "0021601198", "GAME_DATE": "APR 09, 2017", "MATCHUP": "OKC @ DEN", "WL": "W", "MIN": 240, "FGM": 40, "FGA": 96, "FG_PCT": 0.417, "FG3M": 6, "FG3A": 25, "FG3_PCT": 0.24, "FTM": 20, "FTA": 22, "FT_PCT": 0.909, "OREB": 18, "DREB": 36, "REB": 54, "AST": 19, "STL": 7, "BLK": 3, "TOV": 12, "PF": 19, "PTS": 106}, {"Team_ID": 1610612760, "Game_ID": "0021601186", "GAME_DATE": "APR 07, 2017", "MATCHUP": "OKC @ PHX", "WL": "L", "MIN": 240, "FGM": 34, "FGA": 92, "FG_PCT": 0.37, "FG3M": 7, "FG3A": 30, "FG3_PCT": 0.23333333333333334, "FTM": 24, "FTA": 33, "FT_PCT": 0.727, "OREB": 22, "DREB": 26, "REB": 48, "AST": 13, "STL": 1, "BLK": 3, "TOV": 9, "PF": 26, "PTS": 99}, {"Team_ID": 1610612760, "Game_ID": "0021601167", "GAME_DATE": "APR 05, 2017", "MATCHUP": "OKC @ MEM", "WL": "W", "MIN": 240, "FGM": 37, "FGA": 85, "FG_PCT": 0.435, "FG3M": 14, "FG3A": 31, "FG3_PCT": 0.45161290322580644, "FTM": 15, "FTA": 24, "FT_PCT": 0.625, "OREB": 12, "DREB": 32, "REB": 44, "AST": 19, "STL": 8, "BLK": 3, "TOV": 12, "PF": 20, "PTS": 103}, {"Team_ID": 1610612760, "Game_ID": "0021601159", "GAME_DATE": "APR 04, 2017", "MATCHUP": "OKC vs. MIL", "WL": "W", "MIN": 240, "FGM": 40, "FGA": 84, "FG_PCT": 0.476, "FG3M": 9, "FG3A": 28, "FG3_PCT": 0.32142857142857145, "FTM": 21, "FTA": 25, "FT_PCT": 0.84, "OREB": 11, "DREB": 42, "REB": 53, "AST": 29, "STL": 9, "BLK": 7, "TOV": 13, "PF": 20, "PTS": 110}, {"Team_ID": 1610612760, "Game_ID": "0021601142", "GAME_DATE": "APR 02, 2017", "MATCHUP": "OKC vs. CHA", "WL": "L", "MIN": 240, "FGM": 39, "FGA": 84, "FG_PCT": 0.464, "FG3M": 12, "FG3A": 31, "FG3_PCT": 0.3870967741935484, "FTM": 11, "FTA": 12, "FT_PCT": 0.917, "OREB": 7, "DREB": 35, "REB": 42, "AST": 19, "STL": 10, "BLK": 5, "TOV": 24, "PF": 20, "PTS": 101}, {"Team_ID": 1610612760, "Game_ID": "0021601135", "GAME_DATE": "MAR 31, 2017", "MATCHUP": "OKC vs. SAS", "WL": "L", "MIN": 240, "FGM": 33, "FGA": 81, "FG_PCT": 0.407, "FG3M": 6, "FG3A": 21, "FG3_PCT": 0.2857142857142857, "FTM": 23, "FTA": 27, "FT_PCT": 0.852, "OREB": 13, "DREB": 33, "REB": 46, "AST": 21, "STL": 7, "BLK": 3, "TOV": 18, "PF": 21, "PTS": 95}, {"Team_ID": 1610612760, "Game_ID": "0021601112", "GAME_DATE": "MAR 29, 2017", "MATCHUP": "OKC @ ORL", "WL": "W", "MIN": 265, "FGM": 43, "FGA": 102, "FG_PCT": 0.422, "FG3M": 10, "FG3A": 33, "FG3_PCT": 0.30303030303030304, "FTM": 18, "FTA": 28, "FT_PCT": 0.643, "OREB": 11, "DREB": 46, "REB": 57, "AST": 18, "STL": 11, "BLK": 7, "TOV": 11, "PF": 20, "PTS": 114}, {"Team_ID": 1610612760, "Game_ID": "0021601100", "GAME_DATE": "MAR 27, 2017", "MATCHUP": "OKC @ DAL", "WL": "W", "MIN": 240, "FGM": 37, "FGA": 85, "FG_PCT": 0.435, "FG3M": 6, "FG3A": 23, "FG3_PCT": 0.2608695652173913, "FTM": 12, "FTA": 14, "FT_PCT": 0.857, "OREB": 11, "DREB": 37, "REB": 48, "AST": 17, "STL": 10, "BLK": 7, "TOV": 17, "PF": 21, "PTS": 92}, {"Team_ID": 1610612760, "Game_ID": "0021601091", "GAME_DATE": "MAR 26, 2017", "MATCHUP": "OKC @ HOU", "WL": "L", "MIN": 240, "FGM": 47, "FGA": 94, "FG_PCT": 0.5, "FG3M": 11, "FG3A": 30, "FG3_PCT": 0.36666666666666664, "FTM": 20, "FTA": 28, "FT_PCT": 0.714, "OREB": 15, "DREB": 26, "REB": 41, "AST": 27, "STL": 15, "BLK": 3, "TOV": 16, "PF": 21, "PTS": 125}, {"Team_ID": 1610612760, "Game_ID": "0021601062", "GAME_DATE": "MAR 22, 2017", "MATCHUP": "OKC vs. PHI", "WL": "W", "MIN": 240, "FGM": 48, "FGA": 88, "FG_PCT": 0.545, "FG3M": 4, "FG3A": 16, "FG3_PCT": 0.25, "FTM": 22, "FTA": 30, "FT_PCT": 0.733, "OREB": 18, "DREB": 36, "REB": 54, "AST": 26, "STL": 7, "BLK": 8, "TOV": 16, "PF": 17, "PTS": 122}, {"Team_ID": 1610612760, "Game_ID": "0021601049", "GAME_DATE": "MAR 20, 2017", "MATCHUP": "OKC vs. GSW", "WL": "L", "MIN": 240, "FGM": 37, "FGA": 87, "FG_PCT": 0.425, "FG3M": 4, "FG3A": 21, "FG3_PCT": 0.19047619047619047, "FTM": 17, "FTA": 31, "FT_PCT": 0.548, "OREB": 12, "DREB": 28, "REB": 40, "AST": 18, "STL": 10, "BLK": 2, "TOV": 11, "PF": 19, "PTS": 95}, {"Team_ID": 1610612760, "Game_ID": "0021601028", "GAME_DATE": "MAR 18, 2017", "MATCHUP": "OKC vs. SAC", "WL": "W", "MIN": 240, "FGM": 41, "FGA": 82, "FG_PCT": 0.5, "FG3M": 10, "FG3A": 26, "FG3_PCT": 0.38461538461538464, "FTM": 18, "FTA": 25, "FT_PCT": 0.72, "OREB": 13, "DREB": 36, "REB": 49, "AST": 23, "STL": 7, "BLK": 4, "TOV": 14, "PF": 21, "PTS": 110}, {"Team_ID": 1610612760, "Game_ID": "0021601015", "GAME_DATE": "MAR 16, 2017", "MATCHUP": "OKC @ TOR", "WL": "W", "MIN": 240, "FGM": 47, "FGA": 88, "FG_PCT": 0.534, "FG3M": 14, "FG3A": 25, "FG3_PCT": 0.56, "FTM": 15, "FTA": 19, "FT_PCT": 0.789, "OREB": 10, "DREB": 37, "REB": 47, "AST": 33, "STL": 10, "BLK": 1, "TOV": 18, "PF": 22, "PTS": 123}, {"Team_ID": 1610612760, "Game_ID": "0021601000", "GAME_DATE": "MAR 14, 2017", "MATCHUP": "OKC @ BKN", "WL": "W", "MIN": 240, "FGM": 44, "FGA": 89, "FG_PCT": 0.494, "FG3M": 10, "FG3A": 22, "FG3_PCT": 0.45454545454545453, "FTM": 24, "FTA": 34, "FT_PCT": 0.706, "OREB": 13, "DREB": 31, "REB": 44, "AST": 30, "STL": 13, "BLK": 6, "TOV": 13, "PF": 27, "PTS": 122}, {"Team_ID": 1610612760, "Game_ID": "0021600973", "GAME_DATE": "MAR 11, 2017", "MATCHUP": "OKC vs. UTA", "WL": "W", "MIN": 240, "FGM": 43, "FGA": 86, "FG_PCT": 0.5, "FG3M": 8, "FG3A": 23, "FG3_PCT": 0.34782608695652173, "FTM": 18, "FTA": 24, "FT_PCT": 0.75, "OREB": 12, "DREB": 31, "REB": 43, "AST": 23, "STL": 7, "BLK": 7, "TOV": 12, "PF": 20, "PTS": 112}, {"Team_ID": 1610612760, "Game_ID": "0021600962", "GAME_DATE": "MAR 09, 2017", "MATCHUP": "OKC vs. SAS", "WL": "W", "MIN": 240, "FGM": 41, "FGA": 89, "FG_PCT": 0.461, "FG3M": 6, "FG3A": 20, "FG3_PCT": 0.3, "FTM": 14, "FTA": 21, "FT_PCT": 0.667, "OREB": 15, "DREB": 33, "REB": 48, "AST": 23, "STL": 10, "BLK": 3, "TOV": 11, "PF": 22, "PTS": 102}, {"Team_ID": 1610612760, "Game_ID": "0021600946", "GAME_DATE": "MAR 07, 2017", "MATCHUP": "OKC vs. POR", "WL": "L", "MIN": 240, "FGM": 44, "FGA": 85, "FG_PCT": 0.518, "FG3M": 10, "FG3A": 25, "FG3_PCT": 0.4, "FTM": 23, "FTA": 30, "FT_PCT": 0.767, "OREB": 12, "DREB": 27, "REB": 39, "AST": 16, "STL": 4, "BLK": 1, "TOV": 17, "PF": 25, "PTS": 121}, {"Team_ID": 1610612760, "Game_ID": "0021600932", "GAME_DATE": "MAR 05, 2017", "MATCHUP": "OKC @ DAL", "WL": "L", "MIN": 240, "FGM": 33, "FGA": 82, "FG_PCT": 0.402, "FG3M": 2, "FG3A": 22, "FG3_PCT": 0.09090909090909091, "FTM": 21, "FTA": 30, "FT_PCT": 0.7, "OREB": 13, "DREB": 36, "REB": 49, "AST": 19, "STL": 4, "BLK": 2, "TOV": 15, "PF": 21, "PTS": 89}, {"Team_ID": 1610612760, "Game_ID": "0021600916", "GAME_DATE": "MAR 03, 2017", "MATCHUP": "OKC @ PHX", "WL": "L", "MIN": 240, "FGM": 37, "FGA": 87, "FG_PCT": 0.425, "FG3M": 9, "FG3A": 35, "FG3_PCT": 0.2571428571428571, "FTM": 28, "FTA": 35, "FT_PCT": 0.8, "OREB": 11, "DREB": 36, "REB": 47, "AST": 14, "STL": 10, "BLK": 5, "TOV": 19, "PF": 30, "PTS": 111}, {"Team_ID": 1610612760, "Game_ID": "0021600908", "GAME_DATE": "MAR 02, 2017", "MATCHUP": "OKC @ POR", "WL": "L", "MIN": 240, "FGM": 34, "FGA": 86, "FG_PCT": 0.395, "FG3M": 11, "FG3A": 29, "FG3_PCT": 0.3793103448275862, "FTM": 30, "FTA": 32, "FT_PCT": 0.938, "OREB": 12, "DREB": 28, "REB": 40, "AST": 11, "STL": 9, "BLK": 7, "TOV": 12, "PF": 25, "PTS": 109}, {"Team_ID": 1610612760, "Game_ID": "0021600893", "GAME_DATE": "FEB 28, 2017", "MATCHUP": "OKC vs. UTA", "WL": "W", "MIN": 240, "FGM": 39, "FGA": 76, "FG_PCT": 0.513, "FG3M": 15, "FG3A": 22, "FG3_PCT": 0.6818181818181818, "FTM": 16, "FTA": 23, "FT_PCT": 0.696, "OREB": 6, "DREB": 36, "REB": 42, "AST": 20, "STL": 5, "BLK": 7, "TOV": 14, "PF": 17, "PTS": 109}, {"Team_ID": 1610612760, "Game_ID": "0021600880", "GAME_DATE": "FEB 26, 2017", "MATCHUP": "OKC vs. NOP", "WL": "W", "MIN": 240, "FGM": 42, "FGA": 88, "FG_PCT": 0.477, "FG3M": 6, "FG3A": 21, "FG3_PCT": 0.2857142857142857, "FTM": 28, "FTA": 37, "FT_PCT": 0.757, "OREB": 16, "DREB": 37, "REB": 53, "AST": 17, "STL": 4, "BLK": 0, "TOV": 13, "PF": 29, "PTS": 118}, {"Team_ID": 1610612760, "Game_ID": "0021600861", "GAME_DATE": "FEB 24, 2017", "MATCHUP": "OKC vs. LAL", "WL": "W", "MIN": 240, "FGM": 44, "FGA": 97, "FG_PCT": 0.454, "FG3M": 10, "FG3A": 24, "FG3_PCT": 0.4166666666666667, "FTM": 12, "FTA": 17, "FT_PCT": 0.706, "OREB": 14, "DREB": 45, "REB": 59, "AST": 28, "STL": 9, "BLK": 6, "TOV": 17, "PF": 14, "PTS": 110}, {"Team_ID": 1610612760, "Game_ID": "0021600845", "GAME_DATE": "FEB 15, 2017", "MATCHUP": "OKC vs. NYK", "WL": "W", "MIN": 240, "FGM": 41, "FGA": 88, "FG_PCT": 0.466, "FG3M": 12, "FG3A": 23, "FG3_PCT": 0.5217391304347826, "FTM": 22, "FTA": 31, "FT_PCT": 0.71, "OREB": 12, "DREB": 36, "REB": 48, "AST": 21, "STL": 10, "BLK": 4, "TOV": 12, "PF": 13, "PTS": 116}, {"Team_ID": 1610612760, "Game_ID": "0021600820", "GAME_DATE": "FEB 13, 2017", "MATCHUP": "OKC @ WAS", "WL": "L", "MIN": 240, "FGM": 34, "FGA": 96, "FG_PCT": 0.354, "FG3M": 7, "FG3A": 34, "FG3_PCT": 0.20588235294117646, "FTM": 23, "FTA": 30, "FT_PCT": 0.767, "OREB": 20, "DREB": 27, "REB": 47, "AST": 16, "STL": 10, "BLK": 2, "TOV": 15, "PF": 22, "PTS": 98}, {"Team_ID": 1610612760, "Game_ID": "0021600813", "GAME_DATE": "FEB 11, 2017", "MATCHUP": "OKC vs. GSW", "WL": "L", "MIN": 240, "FGM": 40, "FGA": 83, "FG_PCT": 0.482, "FG3M": 6, "FG3A": 24, "FG3_PCT": 0.25, "FTM": 28, "FTA": 36, "FT_PCT": 0.778, "OREB": 12, "DREB": 31, "REB": 43, "AST": 20, "STL": 7, "BLK": 8, "TOV": 19, "PF": 23, "PTS": 114}, {"Team_ID": 1610612760, "Game_ID": "0021600796", "GAME_DATE": "FEB 09, 2017", "MATCHUP": "OKC vs. CLE", "WL": "W", "MIN": 240, "FGM": 50, "FGA": 106, "FG_PCT": 0.472, "FG3M": 8, "FG3A": 27, "FG3_PCT": 0.2962962962962963, "FTM": 10, "FTA": 13, "FT_PCT": 0.769, "OREB": 17, "DREB": 34, "REB": 51, "AST": 24, "STL": 10, "BLK": 5, "TOV": 13, "PF": 23, "PTS": 118}, {"Team_ID": 1610612760, "Game_ID": "0021600770", "GAME_DATE": "FEB 06, 2017", "MATCHUP": "OKC @ IND", "WL": "L", "MIN": 240, "FGM": 34, "FGA": 88, "FG_PCT": 0.386, "FG3M": 7, "FG3A": 28, "FG3_PCT": 0.25, "FTM": 15, "FTA": 21, "FT_PCT": 0.714, "OREB": 20, "DREB": 41, "REB": 61, "AST": 17, "STL": 6, "BLK": 11, "TOV": 16, "PF": 21, "PTS": 90}, {"Team_ID": 1610612760, "Game_ID": "0021600767", "GAME_DATE": "FEB 05, 2017", "MATCHUP": "OKC vs. POR", "WL": "W", "MIN": 240, "FGM": 40, "FGA": 98, "FG_PCT": 0.408, "FG3M": 4, "FG3A": 18, "FG3_PCT": 0.2222222222222222, "FTM": 21, "FTA": 28, "FT_PCT": 0.75, "OREB": 17, "DREB": 39, "REB": 56, "AST": 18, "STL": 9, "BLK": 5, "TOV": 12, "PF": 17, "PTS": 105}, {"Team_ID": 1610612760, "Game_ID": "0021600750", "GAME_DATE": "FEB 03, 2017", "MATCHUP": "OKC vs. MEM", "WL": "W", "MIN": 240, "FGM": 38, "FGA": 80, "FG_PCT": 0.475, "FG3M": 13, "FG3A": 26, "FG3_PCT": 0.5, "FTM": 25, "FTA": 33, "FT_PCT": 0.758, "OREB": 16, "DREB": 31, "REB": 47, "AST": 21, "STL": 7, "BLK": 3, "TOV": 20, "PF": 21, "PTS": 114}, {"Team_ID": 1610612760, "Game_ID": "0021600740", "GAME_DATE": "FEB 01, 2017", "MATCHUP": "OKC vs. CHI", "WL": "L", "MIN": 240, "FGM": 38, "FGA": 100, "FG_PCT": 0.38, "FG3M": 10, "FG3A": 37, "FG3_PCT": 0.2702702702702703, "FTM": 14, "FTA": 17, "FT_PCT": 0.824, "OREB": 11, "DREB": 26, "REB": 37, "AST": 17, "STL": 6, "BLK": 4, "TOV": 9, "PF": 23, "PTS": 100}, {"Team_ID": 1610612760, "Game_ID": "0021600727", "GAME_DATE": "JAN 31, 2017", "MATCHUP": "OKC @ SAS", "WL": "L", "MIN": 240, "FGM": 30, "FGA": 85, "FG_PCT": 0.353, "FG3M": 7, "FG3A": 28, "FG3_PCT": 0.25, "FTM": 27, "FTA": 32, "FT_PCT": 0.844, "OREB": 12, "DREB": 38, "REB": 50, "AST": 21, "STL": 12, "BLK": 7, "TOV": 20, "PF": 30, "PTS": 94}, {"Team_ID": 1610612760, "Game_ID": "0021600712", "GAME_DATE": "JAN 29, 2017", "MATCHUP": "OKC @ CLE", "WL": "L", "MIN": 240, "FGM": 37, "FGA": 100, "FG_PCT": 0.37, "FG3M": 6, "FG3A": 26, "FG3_PCT": 0.23076923076923078, "FTM": 11, "FTA": 16, "FT_PCT": 0.688, "OREB": 13, "DREB": 42, "REB": 55, "AST": 20, "STL": 5, "BLK": 4, "TOV": 16, "PF": 19, "PTS": 91}, {"Team_ID": 1610612760, "Game_ID": "0021600690", "GAME_DATE": "JAN 26, 2017", "MATCHUP": "OKC vs. DAL", "WL": "W", "MIN": 240, "FGM": 37, "FGA": 72, "FG_PCT": 0.514, "FG3M": 9, "FG3A": 22, "FG3_PCT": 0.4090909090909091, "FTM": 26, "FTA": 36, "FT_PCT": 0.722, "OREB": 7, "DREB": 36, "REB": 43, "AST": 13, "STL": 7, "BLK": 2, "TOV": 16, "PF": 17, "PTS": 109}, {"Team_ID": 1610612760, "Game_ID": "0021600686", "GAME_DATE": "JAN 25, 2017", "MATCHUP": "OKC @ NOP", "WL": "W", "MIN": 240, "FGM": 42, "FGA": 91, "FG_PCT": 0.462, "FG3M": 10, "FG3A": 27, "FG3_PCT": 0.37037037037037035, "FTM": 20, "FTA": 28, "FT_PCT": 0.714, "OREB": 12, "DREB": 43, "REB": 55, "AST": 24, "STL": 6, "BLK": 11, "TOV": 16, "PF": 18, "PTS": 114}, {"Team_ID": 1610612760, "Game_ID": "0021600673", "GAME_DATE": "JAN 23, 2017", "MATCHUP": "OKC @ UTA", "WL": "W", "MIN": 240, "FGM": 36, "FGA": 83, "FG_PCT": 0.434, "FG3M": 6, "FG3A": 20, "FG3_PCT": 0.3, "FTM": 19, "FTA": 25, "FT_PCT": 0.76, "OREB": 8, "DREB": 37, "REB": 45, "AST": 17, "STL": 6, "BLK": 6, "TOV": 10, "PF": 23, "PTS": 97}, {"Team_ID": 1610612760, "Game_ID": "0021600634", "GAME_DATE": "JAN 18, 2017", "MATCHUP": "OKC @ GSW", "WL": "L", "MIN": 240, "FGM": 38, "FGA": 90, "FG_PCT": 0.422, "FG3M": 8, "FG3A": 28, "FG3_PCT": 0.2857142857142857, "FTM": 16, "FTA": 19, "FT_PCT": 0.842, "OREB": 13, "DREB": 23, "REB": 36, "AST": 23, "STL": 11, "BLK": 6, "TOV": 18, "PF": 22, "PTS": 100}, {"Team_ID": 1610612760, "Game_ID": "0021600621", "GAME_DATE": "JAN 16, 2017", "MATCHUP": "OKC @ LAC", "WL": "L", "MIN": 240, "FGM": 36, "FGA": 85, "FG_PCT": 0.424, "FG3M": 10, "FG3A": 30, "FG3_PCT": 0.3333333333333333, "FTM": 16, "FTA": 19, "FT_PCT": 0.842, "OREB": 9, "DREB": 27, "REB": 36, "AST": 18, "STL": 10, "BLK": 4, "TOV": 15, "PF": 15, "PTS": 98}, {"Team_ID": 1610612760, "Game_ID": "0021600610", "GAME_DATE": "JAN 15, 2017", "MATCHUP": "OKC @ SAC", "WL": "W", "MIN": 240, "FGM": 40, "FGA": 90, "FG_PCT": 0.444, "FG3M": 9, "FG3A": 28, "FG3_PCT": 0.32142857142857145, "FTM": 33, "FTA": 41, "FT_PCT": 0.805, "OREB": 17, "DREB": 27, "REB": 44, "AST": 20, "STL": 14, "BLK": 4, "TOV": 19, "PF": 28, "PTS": 122}, {"Team_ID": 1610612760, "Game_ID": "0021600596", "GAME_DATE": "JAN 13, 2017", "MATCHUP": "OKC @ MIN", "WL": "L", "MIN": 240, "FGM": 33, "FGA": 85, "FG_PCT": 0.388, "FG3M": 3, "FG3A": 20, "FG3_PCT": 0.15, "FTM": 17, "FTA": 21, "FT_PCT": 0.81, "OREB": 16, "DREB": 31, "REB": 47, "AST": 19, "STL": 10, "BLK": 2, "TOV": 18, "PF": 21, "PTS": 86}, {"Team_ID": 1610612760, "Game_ID": "0021600581", "GAME_DATE": "JAN 11, 2017", "MATCHUP": "OKC vs. MEM", "WL": "W", "MIN": 240, "FGM": 36, "FGA": 81, "FG_PCT": 0.444, "FG3M": 8, "FG3A": 26, "FG3_PCT": 0.3076923076923077, "FTM": 23, "FTA": 29, "FT_PCT": 0.793, "OREB": 11, "DREB": 42, "REB": 53, "AST": 21, "STL": 5, "BLK": 4, "TOV": 16, "PF": 18, "PTS": 103}, {"Team_ID": 1610612760, "Game_ID": "0021600569", "GAME_DATE": "JAN 09, 2017", "MATCHUP": "OKC @ CHI", "WL": "W", "MIN": 240, "FGM": 47, "FGA": 83, "FG_PCT": 0.566, "FG3M": 7, "FG3A": 24, "FG3_PCT": 0.2916666666666667, "FTM": 8, "FTA": 11, "FT_PCT": 0.727, "OREB": 6, "DREB": 36, "REB": 42, "AST": 30, "STL": 5, "BLK": 5, "TOV": 12, "PF": 17, "PTS": 109}, {"Team_ID": 1610612760, "Game_ID": "0021600555", "GAME_DATE": "JAN 07, 2017", "MATCHUP": "OKC vs. DEN", "WL": "W", "MIN": 240, "FGM": 43, "FGA": 89, "FG_PCT": 0.483, "FG3M": 12, "FG3A": 36, "FG3_PCT": 0.3333333333333333, "FTM": 23, "FTA": 29, "FT_PCT": 0.793, "OREB": 6, "DREB": 43, "REB": 49, "AST": 23, "STL": 8, "BLK": 11, "TOV": 10, "PF": 20, "PTS": 121}, {"Team_ID": 1610612760, "Game_ID": "0021600540", "GAME_DATE": "JAN 05, 2017", "MATCHUP": "OKC @ HOU", "WL": "L", "MIN": 240, "FGM": 41, "FGA": 91, "FG_PCT": 0.451, "FG3M": 12, "FG3A": 30, "FG3_PCT": 0.4, "FTM": 22, "FTA": 27, "FT_PCT": 0.815, "OREB": 16, "DREB": 38, "REB": 54, "AST": 15, "STL": 6, "BLK": 9, "TOV": 9, "PF": 21, "PTS": 116}, {"Team_ID": 1610612760, "Game_ID": "0021600529", "GAME_DATE": "JAN 04, 2017", "MATCHUP": "OKC @ CHA", "WL": "L", "MIN": 240, "FGM": 42, "FGA": 96, "FG_PCT": 0.438, "FG3M": 9, "FG3A": 30, "FG3_PCT": 0.3, "FTM": 19, "FTA": 23, "FT_PCT": 0.826, "OREB": 14, "DREB": 37, "REB": 51, "AST": 22, "STL": 6, "BLK": 3, "TOV": 14, "PF": 31, "PTS": 112}, {"Team_ID": 1610612760, "Game_ID": "0021600513", "GAME_DATE": "JAN 02, 2017", "MATCHUP": "OKC @ MIL", "WL": "L", "MIN": 240, "FGM": 36, "FGA": 78, "FG_PCT": 0.462, "FG3M": 9, "FG3A": 27, "FG3_PCT": 0.3333333333333333, "FTM": 13, "FTA": 19, "FT_PCT": 0.684, "OREB": 8, "DREB": 32, "REB": 40, "AST": 20, "STL": 7, "BLK": 5, "TOV": 10, "PF": 20, "PTS": 94}, {"Team_ID": 1610612760, "Game_ID": "0021600507", "GAME_DATE": "DEC 31, 2016", "MATCHUP": "OKC vs. LAC", "WL": "W", "MIN": 240, "FGM": 37, "FGA": 78, "FG_PCT": 0.474, "FG3M": 10, "FG3A": 29, "FG3_PCT": 0.3448275862068966, "FTM": 30, "FTA": 35, "FT_PCT": 0.857, "OREB": 8, "DREB": 36, "REB": 44, "AST": 25, "STL": 9, "BLK": 6, "TOV": 9, "PF": 20, "PTS": 114}, {"Team_ID": 1610612760, "Game_ID": "0021600487", "GAME_DATE": "DEC 29, 2016", "MATCHUP": "OKC @ MEM", "WL": "L", "MIN": 240, "FGM": 25, "FGA": 74, "FG_PCT": 0.338, "FG3M": 4, "FG3A": 22, "FG3_PCT": 0.18181818181818182, "FTM": 26, "FTA": 38, "FT_PCT": 0.684, "OREB": 14, "DREB": 25, "REB": 39, "AST": 9, "STL": 5, "BLK": 7, "TOV": 18, "PF": 18, "PTS": 80}, {"Team_ID": 1610612760, "Game_ID": "0021600473", "GAME_DATE": "DEC 27, 2016", "MATCHUP": "OKC @ MIA", "WL": "W", "MIN": 240, "FGM": 42, "FGA": 82, "FG_PCT": 0.512, "FG3M": 5, "FG3A": 19, "FG3_PCT": 0.2631578947368421, "FTM": 17, "FTA": 25, "FT_PCT": 0.68, "OREB": 14, "DREB": 32, "REB": 46, "AST": 21, "STL": 3, "BLK": 4, "TOV": 17, "PF": 21, "PTS": 106}, {"Team_ID": 1610612760, "Game_ID": "0021600459", "GAME_DATE": "DEC 25, 2016", "MATCHUP": "OKC vs. MIN", "WL": "W", "MIN": 240, "FGM": 42, "FGA": 82, "FG_PCT": 0.512, "FG3M": 8, "FG3A": 24, "FG3_PCT": 0.3333333333333333, "FTM": 20, "FTA": 24, "FT_PCT": 0.833, "OREB": 9, "DREB": 33, "REB": 42, "AST": 26, "STL": 8, "BLK": 4, "TOV": 15, "PF": 24, "PTS": 112}, {"Team_ID": 1610612760, "Game_ID": "0021600445", "GAME_DATE": "DEC 23, 2016", "MATCHUP": "OKC @ BOS", "WL": "W", "MIN": 240, "FGM": 41, "FGA": 80, "FG_PCT": 0.513, "FG3M": 11, "FG3A": 26, "FG3_PCT": 0.4230769230769231, "FTM": 24, "FTA": 36, "FT_PCT": 0.667, "OREB": 10, "DREB": 34, "REB": 44, "AST": 27, "STL": 5, "BLK": 6, "TOV": 13, "PF": 21, "PTS": 117}, {"Team_ID": 1610612760, "Game_ID": "0021600433", "GAME_DATE": "DEC 21, 2016", "MATCHUP": "OKC @ NOP", "WL": "W", "MIN": 240, "FGM": 45, "FGA": 88, "FG_PCT": 0.511, "FG3M": 11, "FG3A": 28, "FG3_PCT": 0.39285714285714285, "FTM": 20, "FTA": 24, "FT_PCT": 0.833, "OREB": 13, "DREB": 36, "REB": 49, "AST": 22, "STL": 8, "BLK": 6, "TOV": 10, "PF": 20, "PTS": 121}, {"Team_ID": 1610612760, "Game_ID": "0021600415", "GAME_DATE": "DEC 19, 2016", "MATCHUP": "OKC vs. ATL", "WL": "L", "MIN": 240, "FGM": 39, "FGA": 87, "FG_PCT": 0.448, "FG3M": 10, "FG3A": 35, "FG3_PCT": 0.2857142857142857, "FTM": 20, "FTA": 26, "FT_PCT": 0.769, "OREB": 15, "DREB": 29, "REB": 44, "AST": 13, "STL": 8, "BLK": 3, "TOV": 12, "PF": 18, "PTS": 108}, {"Team_ID": 1610612760, "Game_ID": "0021600399", "GAME_DATE": "DEC 17, 2016", "MATCHUP": "OKC vs. PHX", "WL": "W", "MIN": 240, "FGM": 41, "FGA": 81, "FG_PCT": 0.506, "FG3M": 7, "FG3A": 16, "FG3_PCT": 0.4375, "FTM": 25, "FTA": 34, "FT_PCT": 0.735, "OREB": 10, "DREB": 32, "REB": 42, "AST": 28, "STL": 12, "BLK": 4, "TOV": 13, "PF": 21, "PTS": 114}, {"Team_ID": 1610612760, "Game_ID": "0021600382", "GAME_DATE": "DEC 14, 2016", "MATCHUP": "OKC @ UTA", "WL": "L", "MIN": 240, "FGM": 30, "FGA": 82, "FG_PCT": 0.366, "FG3M": 6, "FG3A": 19, "FG3_PCT": 0.3157894736842105, "FTM": 23, "FTA": 27, "FT_PCT": 0.852, "OREB": 13, "DREB": 25, "REB": 38, "AST": 14, "STL": 4, "BLK": 3, "TOV": 9, "PF": 18, "PTS": 89}, {"Team_ID": 1610612760, "Game_ID": "0021600373", "GAME_DATE": "DEC 13, 2016", "MATCHUP": "OKC @ POR", "WL": "L", "MIN": 240, "FGM": 33, "FGA": 87, "FG_PCT": 0.379, "FG3M": 8, "FG3A": 27, "FG3_PCT": 0.2962962962962963, "FTM": 21, "FTA": 28, "FT_PCT": 0.75, "OREB": 16, "DREB": 27, "REB": 43, "AST": 18, "STL": 10, "BLK": 2, "TOV": 21, "PF": 21, "PTS": 95}, {"Team_ID": 1610612760, "Game_ID": "0021600357", "GAME_DATE": "DEC 11, 2016", "MATCHUP": "OKC vs. BOS", "WL": "W", "MIN": 240, "FGM": 41, "FGA": 83, "FG_PCT": 0.494, "FG3M": 3, "FG3A": 21, "FG3_PCT": 0.14285714285714285, "FTM": 14, "FTA": 27, "FT_PCT": 0.519, "OREB": 15, "DREB": 34, "REB": 49, "AST": 17, "STL": 9, "BLK": 7, "TOV": 12, "PF": 9, "PTS": 99}, {"Team_ID": 1610612760, "Game_ID": "0021600341", "GAME_DATE": "DEC 09, 2016", "MATCHUP": "OKC vs. HOU", "WL": "L", "MIN": 240, "FGM": 34, "FGA": 81, "FG_PCT": 0.42, "FG3M": 7, "FG3A": 28, "FG3_PCT": 0.25, "FTM": 24, "FTA": 31, "FT_PCT": 0.774, "OREB": 9, "DREB": 37, "REB": 46, "AST": 18, "STL": 9, "BLK": 5, "TOV": 17, "PF": 19, "PTS": 99}, {"Team_ID": 1610612760, "Game_ID": "0021600307", "GAME_DATE": "DEC 05, 2016", "MATCHUP": "OKC @ ATL", "WL": "W", "MIN": 240, "FGM": 37, "FGA": 80, "FG_PCT": 0.463, "FG3M": 10, "FG3A": 31, "FG3_PCT": 0.3225806451612903, "FTM": 18, "FTA": 28, "FT_PCT": 0.643, "OREB": 8, "DREB": 35, "REB": 43, "AST": 26, "STL": 9, "BLK": 5, "TOV": 19, "PF": 27, "PTS": 102}, {"Team_ID": 1610612760, "Game_ID": "0021600301", "GAME_DATE": "DEC 04, 2016", "MATCHUP": "OKC vs. NOP", "WL": "W", "MIN": 240, "FGM": 41, "FGA": 89, "FG_PCT": 0.461, "FG3M": 6, "FG3A": 28, "FG3_PCT": 0.21428571428571427, "FTM": 13, "FTA": 26, "FT_PCT": 0.5, "OREB": 11, "DREB": 48, "REB": 59, "AST": 24, "STL": 7, "BLK": 5, "TOV": 15, "PF": 15, "PTS": 101}, {"Team_ID": 1610612760, "Game_ID": "0021600270", "GAME_DATE": "NOV 30, 2016", "MATCHUP": "OKC vs. WAS", "WL": "W", "MIN": 265, "FGM": 46, "FGA": 95, "FG_PCT": 0.484, "FG3M": 12, "FG3A": 30, "FG3_PCT": 0.4, "FTM": 22, "FTA": 31, "FT_PCT": 0.71, "OREB": 9, "DREB": 38, "REB": 47, "AST": 28, "STL": 10, "BLK": 4, "TOV": 13, "PF": 22, "PTS": 126}, {"Team_ID": 1610612760, "Game_ID": "0021600255", "GAME_DATE": "NOV 28, 2016", "MATCHUP": "OKC @ NYK", "WL": "W", "MIN": 240, "FGM": 46, "FGA": 92, "FG_PCT": 0.5, "FG3M": 8, "FG3A": 22, "FG3_PCT": 0.36363636363636365, "FTM": 12, "FTA": 18, "FT_PCT": 0.667, "OREB": 17, "DREB": 36, "REB": 53, "AST": 25, "STL": 4, "BLK": 7, "TOV": 14, "PF": 22, "PTS": 112}, {"Team_ID": 1610612760, "Game_ID": "0021600242", "GAME_DATE": "NOV 26, 2016", "MATCHUP": "OKC vs. DET", "WL": "W", "MIN": 240, "FGM": 42, "FGA": 83, "FG_PCT": 0.506, "FG3M": 8, "FG3A": 23, "FG3_PCT": 0.34782608695652173, "FTM": 14, "FTA": 26, "FT_PCT": 0.538, "OREB": 10, "DREB": 33, "REB": 43, "AST": 23, "STL": 4, "BLK": 3, "TOV": 10, "PF": 16, "PTS": 106}, {"Team_ID": 1610612760, "Game_ID": "0021600235", "GAME_DATE": "NOV 25, 2016", "MATCHUP": "OKC @ DEN", "WL": "W", "MIN": 265, "FGM": 48, "FGA": 96, "FG_PCT": 0.5, "FG3M": 13, "FG3A": 26, "FG3_PCT": 0.5, "FTM": 23, "FTA": 29, "FT_PCT": 0.793, "OREB": 7, "DREB": 33, "REB": 40, "AST": 29, "STL": 11, "BLK": 4, "TOV": 12, "PF": 21, "PTS": 132}, {"Team_ID": 1610612760, "Game_ID": "0021600224", "GAME_DATE": "NOV 23, 2016", "MATCHUP": "OKC @ SAC", "WL": "L", "MIN": 240, "FGM": 32, "FGA": 76, "FG_PCT": 0.421, "FG3M": 7, "FG3A": 25, "FG3_PCT": 0.28, "FTM": 30, "FTA": 38, "FT_PCT": 0.789, "OREB": 5, "DREB": 33, "REB": 38, "AST": 18, "STL": 7, "BLK": 7, "TOV": 9, "PF": 21, "PTS": 101}, {"Team_ID": 1610612760, "Game_ID": "0021600211", "GAME_DATE": "NOV 22, 2016", "MATCHUP": "OKC @ LAL", "WL": "L", "MIN": 240, "FGM": 45, "FGA": 92, "FG_PCT": 0.489, "FG3M": 11, "FG3A": 27, "FG3_PCT": 0.4074074074074074, "FTM": 8, "FTA": 11, "FT_PCT": 0.727, "OREB": 11, "DREB": 29, "REB": 40, "AST": 29, "STL": 11, "BLK": 6, "TOV": 15, "PF": 14, "PTS": 109}, {"Team_ID": 1610612760, "Game_ID": "0021600195", "GAME_DATE": "NOV 20, 2016", "MATCHUP": "OKC vs. IND", "WL": "L", "MIN": 265, "FGM": 44, "FGA": 101, "FG_PCT": 0.436, "FG3M": 10, "FG3A": 36, "FG3_PCT": 0.2777777777777778, "FTM": 13, "FTA": 18, "FT_PCT": 0.722, "OREB": 15, "DREB": 34, "REB": 49, "AST": 28, "STL": 10, "BLK": 7, "TOV": 20, "PF": 23, "PTS": 111}, {"Team_ID": 1610612760, "Game_ID": "0021600178", "GAME_DATE": "NOV 18, 2016", "MATCHUP": "OKC vs. BKN", "WL": "W", "MIN": 240, "FGM": 49, "FGA": 89, "FG_PCT": 0.551, "FG3M": 7, "FG3A": 26, "FG3_PCT": 0.2692307692307692, "FTM": 19, "FTA": 24, "FT_PCT": 0.792, "OREB": 10, "DREB": 36, "REB": 46, "AST": 23, "STL": 9, "BLK": 5, "TOV": 16, "PF": 24, "PTS": 124}, {"Team_ID": 1610612760, "Game_ID": "0021600164", "GAME_DATE": "NOV 16, 2016", "MATCHUP": "OKC vs. HOU", "WL": "W", "MIN": 240, "FGM": 40, "FGA": 84, "FG_PCT": 0.476, "FG3M": 12, "FG3A": 25, "FG3_PCT": 0.48, "FTM": 13, "FTA": 14, "FT_PCT": 0.929, "OREB": 5, "DREB": 39, "REB": 44, "AST": 25, "STL": 7, "BLK": 7, "TOV": 16, "PF": 15, "PTS": 105}, {"Team_ID": 1610612760, "Game_ID": "0021600147", "GAME_DATE": "NOV 14, 2016", "MATCHUP": "OKC @ DET", "WL": "L", "MIN": 240, "FGM": 33, "FGA": 88, "FG_PCT": 0.375, "FG3M": 5, "FG3A": 27, "FG3_PCT": 0.18518518518518517, "FTM": 17, "FTA": 22, "FT_PCT": 0.773, "OREB": 13, "DREB": 38, "REB": 51, "AST": 16, "STL": 3, "BLK": 6, "TOV": 15, "PF": 21, "PTS": 88}, {"Team_ID": 1610612760, "Game_ID": "0021600141", "GAME_DATE": "NOV 13, 2016", "MATCHUP": "OKC vs. ORL", "WL": "L", "MIN": 240, "FGM": 47, "FGA": 92, "FG_PCT": 0.511, "FG3M": 7, "FG3A": 25, "FG3_PCT": 0.28, "FTM": 16, "FTA": 26, "FT_PCT": 0.615, "OREB": 12, "DREB": 30, "REB": 42, "AST": 22, "STL": 4, "BLK": 6, "TOV": 10, "PF": 19, "PTS": 117}, {"Team_ID": 1610612760, "Game_ID": "0021600126", "GAME_DATE": "NOV 11, 2016", "MATCHUP": "OKC vs. LAC", "WL": "L", "MIN": 240, "FGM": 38, "FGA": 88, "FG_PCT": 0.432, "FG3M": 16, "FG3A": 28, "FG3_PCT": 0.5714285714285714, "FTM": 16, "FTA": 19, "FT_PCT": 0.842, "OREB": 9, "DREB": 36, "REB": 45, "AST": 21, "STL": 3, "BLK": 1, "TOV": 16, "PF": 27, "PTS": 108}, {"Team_ID": 1610612760, "Game_ID": "0021600112", "GAME_DATE": "NOV 09, 2016", "MATCHUP": "OKC vs. TOR", "WL": "L", "MIN": 240, "FGM": 31, "FGA": 74, "FG_PCT": 0.419, "FG3M": 12, "FG3A": 34, "FG3_PCT": 0.35294117647058826, "FTM": 28, "FTA": 31, "FT_PCT": 0.903, "OREB": 11, "DREB": 28, "REB": 39, "AST": 18, "STL": 6, "BLK": 5, "TOV": 19, "PF": 21, "PTS": 102}, {"Team_ID": 1610612760, "Game_ID": "0021600097", "GAME_DATE": "NOV 07, 2016", "MATCHUP": "OKC vs. MIA", "WL": "W", "MIN": 240, "FGM": 37, "FGA": 85, "FG_PCT": 0.435, "FG3M": 9, "FG3A": 28, "FG3_PCT": 0.32142857142857145, "FTM": 14, "FTA": 17, "FT_PCT": 0.824, "OREB": 10, "DREB": 37, "REB": 47, "AST": 24, "STL": 8, "BLK": 5, "TOV": 16, "PF": 18, "PTS": 97}, {"Team_ID": 1610612760, "Game_ID": "0021600079", "GAME_DATE": "NOV 05, 2016", "MATCHUP": "OKC vs. MIN", "WL": "W", "MIN": 240, "FGM": 45, "FGA": 86, "FG_PCT": 0.523, "FG3M": 7, "FG3A": 16, "FG3_PCT": 0.4375, "FTM": 15, "FTA": 24, "FT_PCT": 0.625, "OREB": 11, "DREB": 30, "REB": 41, "AST": 24, "STL": 9, "BLK": 9, "TOV": 12, "PF": 21, "PTS": 112}, {"Team_ID": 1610612760, "Game_ID": "0021600069", "GAME_DATE": "NOV 03, 2016", "MATCHUP": "OKC @ GSW", "WL": "L", "MIN": 240, "FGM": 35, "FGA": 87, "FG_PCT": 0.402, "FG3M": 10, "FG3A": 27, "FG3_PCT": 0.37037037037037035, "FTM": 16, "FTA": 28, "FT_PCT": 0.571, "OREB": 13, "DREB": 28, "REB": 41, "AST": 20, "STL": 8, "BLK": 6, "TOV": 16, "PF": 20, "PTS": 96}, {"Team_ID": 1610612760, "Game_ID": "0021600064", "GAME_DATE": "NOV 02, 2016", "MATCHUP": "OKC @ LAC", "WL": "W", "MIN": 240, "FGM": 34, "FGA": 84, "FG_PCT": 0.405, "FG3M": 5, "FG3A": 20, "FG3_PCT": 0.25, "FTM": 12, "FTA": 20, "FT_PCT": 0.6, "OREB": 10, "DREB": 42, "REB": 52, "AST": 14, "STL": 8, "BLK": 4, "TOV": 21, "PF": 24, "PTS": 85}, {"Team_ID": 1610612760, "Game_ID": "0021600040", "GAME_DATE": "OCT 30, 2016", "MATCHUP": "OKC vs. LAL", "WL": "W", "MIN": 240, "FGM": 45, "FGA": 95, "FG_PCT": 0.474, "FG3M": 9, "FG3A": 26, "FG3_PCT": 0.34615384615384615, "FTM": 14, "FTA": 17, "FT_PCT": 0.824, "OREB": 10, "DREB": 35, "REB": 45, "AST": 29, "STL": 15, "BLK": 6, "TOV": 19, "PF": 22, "PTS": 113}, {"Team_ID": 1610612760, "Game_ID": "0021600021", "GAME_DATE": "OCT 28, 2016", "MATCHUP": "OKC vs. PHX", "WL": "W", "MIN": 265, "FGM": 40, "FGA": 96, "FG_PCT": 0.417, "FG3M": 5, "FG3A": 21, "FG3_PCT": 0.23809523809523808, "FTM": 28, "FTA": 38, "FT_PCT": 0.737, "OREB": 14, "DREB": 43, "REB": 57, "AST": 13, "STL": 11, "BLK": 3, "TOV": 22, "PF": 24, "PTS": 113}, {"Team_ID": 1610612760, "Game_ID": "0021600011", "GAME_DATE": "OCT 26, 2016", "MATCHUP": "OKC @ PHI", "WL": "W", "MIN": 240, "FGM": 39, "FGA": 94, "FG_PCT": 0.415, "FG3M": 6, "FG3A": 22, "FG3_PCT": 0.2727272727272727, "FTM": 19, "FTA": 26, "FT_PCT": 0.731, "OREB": 13, "DREB": 40, "REB": 53, "AST": 19, "STL": 7, "BLK": 3, "TOV": 10, "PF": 23, "PTS": 103}]