[{"Team_ID": 1610612762, "Game_ID": "0029301105", "GAME_DATE": "APR 24, 1994", "MATCHUP": "UTH @ LAL", "WL": "W", "MIN": 240, "FGM": 36, "FGA": 82, "FG_PCT": 0.439, "FG3M": 0, "FG3A": 4, "FG3_PCT": 0.0, "FTM": 31, "FTA": 39, "FT_PCT": 0.795, "OREB": 17, "DREB": 31, "REB": 48, "AST": 28, "STL": 13, "BLK": 4, "TOV": 16, "PF": 25, "PTS": 103}, {"Team_ID": 1610612762, "Game_ID": "0029301084", "GAME_DATE": "APR 22, 1994", "MATCHUP": "UTH @ DEN", "WL": "W", "MIN": 240, "FGM": 45, "FGA": 81, "FG_PCT": 0.556, "FG3M": 1, "FG3A": 3, "FG3_PCT": 0.3333333333333333, "FTM": 22, "FTA": 35, "FT_PCT": 0.629, "OREB": 9, "DREB": 24, "REB": 33, "AST": 28, "STL": 13, "BLK": 5, "TOV": 9, "PF": 29, "PTS": 113}, {"Team_ID": 1610612762, "Game_ID": "0029301077", "GAME_DATE": "APR 21, 1994", "MATCHUP": "UTH vs. POR", "WL": "W", "MIN": 240, "FGM": 44, "FGA": 87, "FG_PCT": 0.506, "FG3M": 3, "FG3A": 7, "FG3_PCT": 0.42857142857142855, "FTM": 31, "FTA": 42, "FT_PCT": 0.738, "OREB": 13, "DREB": 33, "REB": 46, "AST": 27, "STL": 4, "BLK": 8, "TOV": 11, "PF": 23, "PTS": 122}, {"Team_ID": 1610612762, "Game_ID": "0029301064", "GAME_DATE": "APR 19, 1994", "MATCHUP": "UTH @ SAC", "WL": "W", "MIN": 240, "FGM": 41, "FGA": 72, "FG_PCT": 0.569, "FG3M": 6, "FG3A": 8, "FG3_PCT": 0.75, "FTM": 27, "FTA": 39, "FT_PCT": 0.692, "OREB": 7, "DREB": 26, "REB": 33, "AST": 30, "STL": 10, "BLK": 2, "TOV": 11, "PF": 25, "PTS": 115}, {"Team_ID": 1610612762, "Game_ID": "0029301046", "GAME_DATE": "APR 16, 1994", "MATCHUP": "UTH @ GOS", "WL": "L", "MIN": 240, "FGM": 42, "FGA": 89, "FG_PCT": 0.472, "FG3M": 3, "FG3A": 7, "FG3_PCT": 0.42857142857142855, "FTM": 18, "FTA": 28, "FT_PCT": 0.643, "OREB": 17, "DREB": 29, "REB": 46, "AST": 24, "STL": 14, "BLK": 1, "TOV": 16, "PF": 28, "PTS": 105}, {"Team_ID": 1610612762, "Game_ID": "0029301033", "GAME_DATE": "APR 14, 1994", "MATCHUP": "UTH vs. SAN", "WL": "W", "MIN": 240, "FGM": 35, "FGA": 72, "FG_PCT": 0.486, "FG3M": 2, "FG3A": 6, "FG3_PCT": 0.3333333333333333, "FTM": 29, "FTA": 39, "FT_PCT": 0.744, "OREB": 11, "DREB": 36, "REB": 47, "AST": 25, "STL": 4, "BLK": 5, "TOV": 10, "PF": 16, "PTS": 101}, {"Team_ID": 1610612762, "Game_ID": "0029301014", "GAME_DATE": "APR 12, 1994", "MATCHUP": "UTH vs. SAC", "WL": "W", "MIN": 240, "FGM": 48, "FGA": 79, "FG_PCT": 0.608, "FG3M": 1, "FG3A": 3, "FG3_PCT": 0.3333333333333333, "FTM": 29, "FTA": 38, "FT_PCT": 0.763, "OREB": 7, "DREB": 34, "REB": 41, "AST": 34, "STL": 8, "BLK": 7, "TOV": 16, "PF": 24, "PTS": 126}, {"Team_ID": 1610612762, "Game_ID": "0029301000", "GAME_DATE": "APR 09, 1994", "MATCHUP": "UTH vs. LAC", "WL": "W", "MIN": 240, "FGM": 50, "FGA": 87, "FG_PCT": 0.575, "FG3M": 2, "FG3A": 3, "FG3_PCT": 0.6666666666666666, "FTM": 26, "FTA": 31, "FT_PCT": 0.839, "OREB": 14, "DREB": 34, "REB": 48, "AST": 33, "STL": 10, "BLK": 4, "TOV": 17, "PF": 31, "PTS": 128}, {"Team_ID": 1610612762, "Game_ID": "0029300983", "GAME_DATE": "APR 07, 1994", "MATCHUP": "UTH vs. DAL", "WL": "W", "MIN": 240, "FGM": 40, "FGA": 97, "FG_PCT": 0.412, "FG3M": 1, "FG3A": 3, "FG3_PCT": 0.3333333333333333, "FTM": 18, "FTA": 27, "FT_PCT": 0.667, "OREB": 23, "DREB": 30, "REB": 53, "AST": 30, "STL": 14, "BLK": 6, "TOV": 13, "PF": 20, "PTS": 99}, {"Team_ID": 1610612762, "Game_ID": "0029300966", "GAME_DATE": "APR 05, 1994", "MATCHUP": "UTH @ SEA", "WL": "L", "MIN": 240, "FGM": 28, "FGA": 65, "FG_PCT": 0.431, "FG3M": 2, "FG3A": 10, "FG3_PCT": 0.2, "FTM": 21, "FTA": 29, "FT_PCT": 0.724, "OREB": 12, "DREB": 27, "REB": 39, "AST": 23, "STL": 7, "BLK": 3, "TOV": 13, "PF": 24, "PTS": 79}, {"Team_ID": 1610612762, "Game_ID": "0029300950", "GAME_DATE": "APR 02, 1994", "MATCHUP": "UTH vs. DEN", "WL": "W", "MIN": 240, "FGM": 33, "FGA": 74, "FG_PCT": 0.446, "FG3M": 6, "FG3A": 10, "FG3_PCT": 0.6, "FTM": 29, "FTA": 39, "FT_PCT": 0.744, "OREB": 7, "DREB": 34, "REB": 41, "AST": 25, "STL": 9, "BLK": 2, "TOV": 15, "PF": 33, "PTS": 101}, {"Team_ID": 1610612762, "Game_ID": "0029300923", "GAME_DATE": "MAR 29, 1994", "MATCHUP": "UTH vs. GOS", "WL": "L", "MIN": 240, "FGM": 46, "FGA": 102, "FG_PCT": 0.451, "FG3M": 7, "FG3A": 14, "FG3_PCT": 0.5, "FTM": 14, "FTA": 20, "FT_PCT": 0.7, "OREB": 25, "DREB": 32, "REB": 57, "AST": 28, "STL": 5, "BLK": 4, "TOV": 15, "PF": 34, "PTS": 113}, {"Team_ID": 1610612762, "Game_ID": "0029300904", "GAME_DATE": "MAR 26, 1994", "MATCHUP": "UTH @ HOU", "WL": "L", "MIN": 240, "FGM": 33, "FGA": 88, "FG_PCT": 0.375, "FG3M": 3, "FG3A": 14, "FG3_PCT": 0.21428571428571427, "FTM": 14, "FTA": 19, "FT_PCT": 0.737, "OREB": 16, "DREB": 30, "REB": 46, "AST": 18, "STL": 9, "BLK": 2, "TOV": 15, "PF": 26, "PTS": 83}, {"Team_ID": 1610612762, "Game_ID": "0029300899", "GAME_DATE": "MAR 25, 1994", "MATCHUP": "UTH vs. MIL", "WL": "W", "MIN": 240, "FGM": 42, "FGA": 74, "FG_PCT": 0.568, "FG3M": 1, "FG3A": 9, "FG3_PCT": 0.1111111111111111, "FTM": 18, "FTA": 24, "FT_PCT": 0.75, "OREB": 6, "DREB": 31, "REB": 37, "AST": 33, "STL": 9, "BLK": 5, "TOV": 15, "PF": 20, "PTS": 103}, {"Team_ID": 1610612762, "Game_ID": "0029300882", "GAME_DATE": "MAR 23, 1994", "MATCHUP": "UTH vs. ORL", "WL": "L", "MIN": 240, "FGM": 32, "FGA": 75, "FG_PCT": 0.427, "FG3M": 2, "FG3A": 7, "FG3_PCT": 0.2857142857142857, "FTM": 27, "FTA": 33, "FT_PCT": 0.818, "OREB": 13, "DREB": 33, "REB": 46, "AST": 22, "STL": 4, "BLK": 3, "TOV": 13, "PF": 25, "PTS": 93}, {"Team_ID": 1610612762, "Game_ID": "0029300871", "GAME_DATE": "MAR 21, 1994", "MATCHUP": "UTH @ ATL", "WL": "L", "MIN": 265, "FGM": 38, "FGA": 98, "FG_PCT": 0.388, "FG3M": 1, "FG3A": 6, "FG3_PCT": 0.16666666666666666, "FTM": 19, "FTA": 23, "FT_PCT": 0.826, "OREB": 23, "DREB": 35, "REB": 58, "AST": 21, "STL": 8, "BLK": 1, "TOV": 21, "PF": 22, "PTS": 96}, {"Team_ID": 1610612762, "Game_ID": "0029300861", "GAME_DATE": "MAR 19, 1994", "MATCHUP": "UTH @ IND", "WL": "L", "MIN": 240, "FGM": 34, "FGA": 71, "FG_PCT": 0.479, "FG3M": 1, "FG3A": 7, "FG3_PCT": 0.14285714285714285, "FTM": 34, "FTA": 43, "FT_PCT": 0.791, "OREB": 7, "DREB": 27, "REB": 34, "AST": 29, "STL": 10, "BLK": 3, "TOV": 9, "PF": 30, "PTS": 103}, {"Team_ID": 1610612762, "Game_ID": "0029300854", "GAME_DATE": "MAR 18, 1994", "MATCHUP": "UTH @ CHH", "WL": "L", "MIN": 240, "FGM": 30, "FGA": 76, "FG_PCT": 0.395, "FG3M": 2, "FG3A": 9, "FG3_PCT": 0.2222222222222222, "FTM": 16, "FTA": 24, "FT_PCT": 0.667, "OREB": 11, "DREB": 30, "REB": 41, "AST": 20, "STL": 6, "BLK": 6, "TOV": 18, "PF": 29, "PTS": 78}, {"Team_ID": 1610612762, "Game_ID": "0029300825", "GAME_DATE": "MAR 15, 1994", "MATCHUP": "UTH @ LAC", "WL": "L", "MIN": 240, "FGM": 44, "FGA": 93, "FG_PCT": 0.473, "FG3M": 3, "FG3A": 14, "FG3_PCT": 0.21428571428571427, "FTM": 14, "FTA": 19, "FT_PCT": 0.737, "OREB": 17, "DREB": 27, "REB": 44, "AST": 33, "STL": 6, "BLK": 5, "TOV": 6, "PF": 22, "PTS": 105}, {"Team_ID": 1610612762, "Game_ID": "0029300824", "GAME_DATE": "MAR 14, 1994", "MATCHUP": "UTH vs. LAL", "WL": "W", "MIN": 240, "FGM": 40, "FGA": 73, "FG_PCT": 0.548, "FG3M": 2, "FG3A": 8, "FG3_PCT": 0.25, "FTM": 20, "FTA": 28, "FT_PCT": 0.714, "OREB": 11, "DREB": 33, "REB": 44, "AST": 26, "STL": 7, "BLK": 2, "TOV": 17, "PF": 22, "PTS": 102}, {"Team_ID": 1610612762, "Game_ID": "0029300789", "GAME_DATE": "MAR 09, 1994", "MATCHUP": "UTH @ POR", "WL": "L", "MIN": 240, "FGM": 41, "FGA": 81, "FG_PCT": 0.506, "FG3M": 2, "FG3A": 9, "FG3_PCT": 0.2222222222222222, "FTM": 15, "FTA": 23, "FT_PCT": 0.652, "OREB": 8, "DREB": 18, "REB": 26, "AST": 29, "STL": 3, "BLK": 1, "TOV": 12, "PF": 25, "PTS": 99}, {"Team_ID": 1610612762, "Game_ID": "0029300782", "GAME_DATE": "MAR 08, 1994", "MATCHUP": "UTH vs. MIN", "WL": "W", "MIN": 240, "FGM": 35, "FGA": 87, "FG_PCT": 0.402, "FG3M": 1, "FG3A": 9, "FG3_PCT": 0.1111111111111111, "FTM": 29, "FTA": 37, "FT_PCT": 0.784, "OREB": 16, "DREB": 28, "REB": 44, "AST": 18, "STL": 9, "BLK": 9, "TOV": 8, "PF": 25, "PTS": 100}, {"Team_ID": 1610612762, "Game_ID": "0029300770", "GAME_DATE": "MAR 06, 1994", "MATCHUP": "UTH @ PHX", "WL": "W", "MIN": 240, "FGM": 42, "FGA": 79, "FG_PCT": 0.532, "FG3M": 2, "FG3A": 7, "FG3_PCT": 0.2857142857142857, "FTM": 17, "FTA": 22, "FT_PCT": 0.773, "OREB": 7, "DREB": 27, "REB": 34, "AST": 28, "STL": 15, "BLK": 2, "TOV": 13, "PF": 29, "PTS": 103}, {"Team_ID": 1610612762, "Game_ID": "0029300767", "GAME_DATE": "MAR 05, 1994", "MATCHUP": "UTH @ DAL", "WL": "W", "MIN": 240, "FGM": 39, "FGA": 75, "FG_PCT": 0.52, "FG3M": 1, "FG3A": 4, "FG3_PCT": 0.25, "FTM": 24, "FTA": 31, "FT_PCT": 0.774, "OREB": 11, "DREB": 32, "REB": 43, "AST": 27, "STL": 7, "BLK": 1, "TOV": 16, "PF": 25, "PTS": 103}, {"Team_ID": 1610612762, "Game_ID": "0029300748", "GAME_DATE": "MAR 02, 1994", "MATCHUP": "UTH @ SAN", "WL": "W", "MIN": 240, "FGM": 41, "FGA": 70, "FG_PCT": 0.586, "FG3M": 4, "FG3A": 8, "FG3_PCT": 0.5, "FTM": 20, "FTA": 24, "FT_PCT": 0.833, "OREB": 8, "DREB": 23, "REB": 31, "AST": 32, "STL": 12, "BLK": 2, "TOV": 12, "PF": 19, "PTS": 106}, {"Team_ID": 1610612762, "Game_ID": "0029300733", "GAME_DATE": "FEB 28, 1994", "MATCHUP": "UTH vs. HOU", "WL": "W", "MIN": 240, "FGM": 32, "FGA": 78, "FG_PCT": 0.41, "FG3M": 2, "FG3A": 6, "FG3_PCT": 0.3333333333333333, "FTM": 23, "FTA": 31, "FT_PCT": 0.742, "OREB": 14, "DREB": 29, "REB": 43, "AST": 22, "STL": 6, "BLK": 3, "TOV": 7, "PF": 19, "PTS": 89}, {"Team_ID": 1610612762, "Game_ID": "0029300722", "GAME_DATE": "FEB 26, 1994", "MATCHUP": "UTH @ HOU", "WL": "W", "MIN": 240, "FGM": 34, "FGA": 75, "FG_PCT": 0.453, "FG3M": 2, "FG3A": 7, "FG3_PCT": 0.2857142857142857, "FTM": 25, "FTA": 34, "FT_PCT": 0.735, "OREB": 12, "DREB": 33, "REB": 45, "AST": 23, "STL": 11, "BLK": 1, "TOV": 16, "PF": 22, "PTS": 95}, {"Team_ID": 1610612762, "Game_ID": "0029300707", "GAME_DATE": "FEB 25, 1994", "MATCHUP": "UTH vs. PHX", "WL": "W", "MIN": 240, "FGM": 43, "FGA": 89, "FG_PCT": 0.483, "FG3M": 4, "FG3A": 11, "FG3_PCT": 0.36363636363636365, "FTM": 17, "FTA": 20, "FT_PCT": 0.364, "OREB": 16, "DREB": 36, "REB": 52, "AST": 24, "STL": 5, "BLK": 10, "TOV": 9, "PF": 22, "PTS": 107}, {"Team_ID": 1610612762, "Game_ID": "0029300700", "GAME_DATE": "FEB 23, 1994", "MATCHUP": "UTH vs. SAN", "WL": "W", "MIN": 290, "FGM": 41, "FGA": 82, "FG_PCT": 0.5, "FG3M": 0, "FG3A": 4, "FG3_PCT": 0.0, "FTM": 24, "FTA": 33, "FT_PCT": 0.727, "OREB": 11, "DREB": 32, "REB": 43, "AST": 24, "STL": 10, "BLK": 5, "TOV": 14, "PF": 22, "PTS": 106}, {"Team_ID": 1610612762, "Game_ID": "0029300684", "GAME_DATE": "FEB 21, 1994", "MATCHUP": "UTH vs. PHL", "WL": "W", "MIN": 240, "FGM": 52, "FGA": 88, "FG_PCT": 0.591, "FG3M": 1, "FG3A": 3, "FG3_PCT": 0.3333333333333333, "FTM": 14, "FTA": 16, "FT_PCT": 0.875, "OREB": 11, "DREB": 31, "REB": 42, "AST": 31, "STL": 11, "BLK": 8, "TOV": 19, "PF": 14, "PTS": 119}, {"Team_ID": 1610612762, "Game_ID": "0029300671", "GAME_DATE": "FEB 19, 1994", "MATCHUP": "UTH vs. LAC", "WL": "W", "MIN": 240, "FGM": 40, "FGA": 89, "FG_PCT": 0.449, "FG3M": 1, "FG3A": 4, "FG3_PCT": 0.25, "FTM": 19, "FTA": 26, "FT_PCT": 0.731, "OREB": 20, "DREB": 39, "REB": 59, "AST": 28, "STL": 9, "BLK": 7, "TOV": 14, "PF": 23, "PTS": 100}, {"Team_ID": 1610612762, "Game_ID": "0029300661", "GAME_DATE": "FEB 18, 1994", "MATCHUP": "UTH @ SAC", "WL": "L", "MIN": 240, "FGM": 31, "FGA": 91, "FG_PCT": 0.341, "FG3M": 0, "FG3A": 6, "FG3_PCT": 0.0, "FTM": 19, "FTA": 32, "FT_PCT": 0.594, "OREB": 20, "DREB": 37, "REB": 57, "AST": 16, "STL": 10, "BLK": 5, "TOV": 13, "PF": 30, "PTS": 81}, {"Team_ID": 1610612762, "Game_ID": "0029300651", "GAME_DATE": "FEB 16, 1994", "MATCHUP": "UTH @ LAC", "WL": "W", "MIN": 240, "FGM": 38, "FGA": 86, "FG_PCT": 0.442, "FG3M": 3, "FG3A": 5, "FG3_PCT": 0.6, "FTM": 24, "FTA": 31, "FT_PCT": 0.774, "OREB": 17, "DREB": 30, "REB": 47, "AST": 26, "STL": 12, "BLK": 3, "TOV": 18, "PF": 27, "PTS": 103}, {"Team_ID": 1610612762, "Game_ID": "0029300624", "GAME_DATE": "FEB 09, 1994", "MATCHUP": "UTH vs. LAL", "WL": "L", "MIN": 240, "FGM": 38, "FGA": 85, "FG_PCT": 0.447, "FG3M": 2, "FG3A": 6, "FG3_PCT": 0.3333333333333333, "FTM": 18, "FTA": 29, "FT_PCT": 0.621, "OREB": 19, "DREB": 27, "REB": 46, "AST": 29, "STL": 9, "BLK": 1, "TOV": 11, "PF": 24, "PTS": 96}, {"Team_ID": 1610612762, "Game_ID": "0029300617", "GAME_DATE": "FEB 08, 1994", "MATCHUP": "UTH @ DEN", "WL": "W", "MIN": 240, "FGM": 37, "FGA": 74, "FG_PCT": 0.5, "FG3M": 2, "FG3A": 8, "FG3_PCT": 0.25, "FTM": 20, "FTA": 28, "FT_PCT": 0.714, "OREB": 9, "DREB": 33, "REB": 42, "AST": 23, "STL": 7, "BLK": 9, "TOV": 18, "PF": 21, "PTS": 96}, {"Team_ID": 1610612762, "Game_ID": "0029300599", "GAME_DATE": "FEB 06, 1994", "MATCHUP": "UTH @ LAL", "WL": "L", "MIN": 240, "FGM": 32, "FGA": 88, "FG_PCT": 0.364, "FG3M": 5, "FG3A": 10, "FG3_PCT": 0.5, "FTM": 21, "FTA": 25, "FT_PCT": 0.84, "OREB": 16, "DREB": 22, "REB": 38, "AST": 21, "STL": 9, "BLK": 4, "TOV": 11, "PF": 26, "PTS": 90}, {"Team_ID": 1610612762, "Game_ID": "0029300593", "GAME_DATE": "FEB 05, 1994", "MATCHUP": "UTH vs. POR", "WL": "W", "MIN": 240, "FGM": 48, "FGA": 77, "FG_PCT": 0.623, "FG3M": 3, "FG3A": 6, "FG3_PCT": 0.5, "FTM": 29, "FTA": 37, "FT_PCT": 0.784, "OREB": 8, "DREB": 30, "REB": 38, "AST": 37, "STL": 7, "BLK": 9, "TOV": 17, "PF": 28, "PTS": 128}, {"Team_ID": 1610612762, "Game_ID": "0029300580", "GAME_DATE": "FEB 03, 1994", "MATCHUP": "UTH vs. CHI", "WL": "L", "MIN": 240, "FGM": 36, "FGA": 70, "FG_PCT": 0.514, "FG3M": 2, "FG3A": 5, "FG3_PCT": 0.4, "FTM": 11, "FTA": 14, "FT_PCT": 0.786, "OREB": 6, "DREB": 25, "REB": 31, "AST": 21, "STL": 8, "BLK": 4, "TOV": 23, "PF": 25, "PTS": 85}, {"Team_ID": 1610612762, "Game_ID": "0029300569", "GAME_DATE": "FEB 01, 1994", "MATCHUP": "UTH vs. HOU", "WL": "W", "MIN": 240, "FGM": 39, "FGA": 77, "FG_PCT": 0.506, "FG3M": 1, "FG3A": 5, "FG3_PCT": 0.2, "FTM": 25, "FTA": 29, "FT_PCT": 0.862, "OREB": 12, "DREB": 33, "REB": 45, "AST": 25, "STL": 10, "BLK": 4, "TOV": 13, "PF": 23, "PTS": 104}, {"Team_ID": 1610612762, "Game_ID": "0029300539", "GAME_DATE": "JAN 28, 1994", "MATCHUP": "UTH vs. GOS", "WL": "W", "MIN": 240, "FGM": 50, "FGA": 98, "FG_PCT": 0.51, "FG3M": 1, "FG3A": 3, "FG3_PCT": 0.3333333333333333, "FTM": 18, "FTA": 29, "FT_PCT": 0.621, "OREB": 18, "DREB": 33, "REB": 51, "AST": 34, "STL": 14, "BLK": 12, "TOV": 15, "PF": 22, "PTS": 119}, {"Team_ID": 1610612762, "Game_ID": "0029300526", "GAME_DATE": "JAN 26, 1994", "MATCHUP": "UTH @ MIN", "WL": "L", "MIN": 240, "FGM": 35, "FGA": 84, "FG_PCT": 0.417, "FG3M": 1, "FG3A": 8, "FG3_PCT": 0.125, "FTM": 27, "FTA": 37, "FT_PCT": 0.73, "OREB": 10, "DREB": 30, "REB": 40, "AST": 24, "STL": 6, "BLK": 7, "TOV": 12, "PF": 32, "PTS": 98}, {"Team_ID": 1610612762, "Game_ID": "0029300516", "GAME_DATE": "JAN 24, 1994", "MATCHUP": "UTH vs. SEA", "WL": "W", "MIN": 240, "FGM": 37, "FGA": 83, "FG_PCT": 0.446, "FG3M": 4, "FG3A": 8, "FG3_PCT": 0.5, "FTM": 17, "FTA": 21, "FT_PCT": 0.81, "OREB": 17, "DREB": 32, "REB": 49, "AST": 29, "STL": 10, "BLK": 6, "TOV": 16, "PF": 25, "PTS": 95}, {"Team_ID": 1610612762, "Game_ID": "0029300501", "GAME_DATE": "JAN 22, 1994", "MATCHUP": "UTH @ HOU", "WL": "L", "MIN": 240, "FGM": 40, "FGA": 84, "FG_PCT": 0.476, "FG3M": 4, "FG3A": 9, "FG3_PCT": 0.4444444444444444, "FTM": 17, "FTA": 24, "FT_PCT": 0.708, "OREB": 9, "DREB": 25, "REB": 34, "AST": 27, "STL": 13, "BLK": 2, "TOV": 10, "PF": 21, "PTS": 101}, {"Team_ID": 1610612762, "Game_ID": "0029300500", "GAME_DATE": "JAN 21, 1994", "MATCHUP": "UTH vs. SAC", "WL": "W", "MIN": 240, "FGM": 42, "FGA": 88, "FG_PCT": 0.477, "FG3M": 2, "FG3A": 7, "FG3_PCT": 0.2857142857142857, "FTM": 26, "FTA": 40, "FT_PCT": 0.286, "OREB": 22, "DREB": 27, "REB": 49, "AST": 32, "STL": 10, "BLK": 6, "TOV": 9, "PF": 22, "PTS": 112}, {"Team_ID": 1610612762, "Game_ID": "0029300479", "GAME_DATE": "JAN 19, 1994", "MATCHUP": "UTH vs. CLE", "WL": "W", "MIN": 240, "FGM": 40, "FGA": 67, "FG_PCT": 0.597, "FG3M": 0, "FG3A": 2, "FG3_PCT": 0.0, "FTM": 24, "FTA": 34, "FT_PCT": 0.706, "OREB": 10, "DREB": 31, "REB": 41, "AST": 25, "STL": 7, "BLK": 7, "TOV": 12, "PF": 20, "PTS": 104}, {"Team_ID": 1610612762, "Game_ID": "0029300470", "GAME_DATE": "JAN 17, 1994", "MATCHUP": "UTH @ DET", "WL": "W", "MIN": 240, "FGM": 41, "FGA": 76, "FG_PCT": 0.539, "FG3M": 4, "FG3A": 8, "FG3_PCT": 0.5, "FTM": 23, "FTA": 33, "FT_PCT": 0.697, "OREB": 11, "DREB": 33, "REB": 44, "AST": 29, "STL": 8, "BLK": 3, "TOV": 16, "PF": 22, "PTS": 109}, {"Team_ID": 1610612762, "Game_ID": "0029300464", "GAME_DATE": "JAN 16, 1994", "MATCHUP": "UTH @ NJN", "WL": "L", "MIN": 240, "FGM": 36, "FGA": 71, "FG_PCT": 0.507, "FG3M": 2, "FG3A": 3, "FG3_PCT": 0.6666666666666666, "FTM": 20, "FTA": 25, "FT_PCT": 0.8, "OREB": 10, "DREB": 27, "REB": 37, "AST": 24, "STL": 10, "BLK": 4, "TOV": 19, "PF": 25, "PTS": 94}, {"Team_ID": 1610612762, "Game_ID": "0029300445", "GAME_DATE": "JAN 14, 1994", "MATCHUP": "UTH @ CHI", "WL": "L", "MIN": 240, "FGM": 40, "FGA": 86, "FG_PCT": 0.465, "FG3M": 0, "FG3A": 4, "FG3_PCT": 0.0, "FTM": 11, "FTA": 21, "FT_PCT": 0.524, "OREB": 15, "DREB": 24, "REB": 39, "AST": 28, "STL": 10, "BLK": 2, "TOV": 11, "PF": 24, "PTS": 91}, {"Team_ID": 1610612762, "Game_ID": "0029300442", "GAME_DATE": "JAN 13, 1994", "MATCHUP": "UTH @ MIL", "WL": "W", "MIN": 240, "FGM": 40, "FGA": 74, "FG_PCT": 0.541, "FG3M": 3, "FG3A": 5, "FG3_PCT": 0.6, "FTM": 18, "FTA": 26, "FT_PCT": 0.692, "OREB": 7, "DREB": 37, "REB": 44, "AST": 27, "STL": 6, "BLK": 7, "TOV": 16, "PF": 25, "PTS": 101}, {"Team_ID": 1610612762, "Game_ID": "0029300411", "GAME_DATE": "JAN 08, 1994", "MATCHUP": "UTH @ SEA", "WL": "L", "MIN": 240, "FGM": 33, "FGA": 71, "FG_PCT": 0.465, "FG3M": 3, "FG3A": 9, "FG3_PCT": 0.3333333333333333, "FTM": 18, "FTA": 25, "FT_PCT": 0.72, "OREB": 9, "DREB": 25, "REB": 34, "AST": 18, "STL": 11, "BLK": 2, "TOV": 20, "PF": 22, "PTS": 87}, {"Team_ID": 1610612762, "Game_ID": "0029300399", "GAME_DATE": "JAN 07, 1994", "MATCHUP": "UTH vs. MIA", "WL": "L", "MIN": 240, "FGM": 35, "FGA": 80, "FG_PCT": 0.438, "FG3M": 4, "FG3A": 16, "FG3_PCT": 0.25, "FTM": 30, "FTA": 39, "FT_PCT": 0.769, "OREB": 14, "DREB": 31, "REB": 45, "AST": 29, "STL": 8, "BLK": 4, "TOV": 16, "PF": 28, "PTS": 104}, {"Team_ID": 1610612762, "Game_ID": "0029300387", "GAME_DATE": "JAN 05, 1994", "MATCHUP": "UTH vs. PHX", "WL": "L", "MIN": 240, "FGM": 39, "FGA": 89, "FG_PCT": 0.438, "FG3M": 3, "FG3A": 7, "FG3_PCT": 0.42857142857142855, "FTM": 10, "FTA": 16, "FT_PCT": 0.625, "OREB": 13, "DREB": 21, "REB": 34, "AST": 28, "STL": 9, "BLK": 3, "TOV": 12, "PF": 19, "PTS": 91}, {"Team_ID": 1610612762, "Game_ID": "0029300374", "GAME_DATE": "JAN 03, 1994", "MATCHUP": "UTH vs. DAL", "WL": "W", "MIN": 240, "FGM": 46, "FGA": 92, "FG_PCT": 0.5, "FG3M": 2, "FG3A": 8, "FG3_PCT": 0.25, "FTM": 21, "FTA": 26, "FT_PCT": 0.808, "OREB": 15, "DREB": 34, "REB": 49, "AST": 33, "STL": 13, "BLK": 7, "TOV": 15, "PF": 18, "PTS": 115}, {"Team_ID": 1610612762, "Game_ID": "0029300373", "GAME_DATE": "JAN 02, 1994", "MATCHUP": "UTH @ POR", "WL": "W", "MIN": 240, "FGM": 39, "FGA": 76, "FG_PCT": 0.513, "FG3M": 0, "FG3A": 5, "FG3_PCT": 0.0, "FTM": 14, "FTA": 21, "FT_PCT": 0.667, "OREB": 7, "DREB": 31, "REB": 38, "AST": 25, "STL": 10, "BLK": 4, "TOV": 17, "PF": 22, "PTS": 92}, {"Team_ID": 1610612762, "Game_ID": "0029300353", "GAME_DATE": "DEC 29, 1993", "MATCHUP": "UTH vs. BOS", "WL": "W", "MIN": 265, "FGM": 41, "FGA": 90, "FG_PCT": 0.456, "FG3M": 4, "FG3A": 7, "FG3_PCT": 0.5714285714285714, "FTM": 24, "FTA": 33, "FT_PCT": 0.727, "OREB": 15, "DREB": 34, "REB": 49, "AST": 33, "STL": 13, "BLK": 5, "TOV": 17, "PF": 27, "PTS": 110}, {"Team_ID": 1610612762, "Game_ID": "0029300340", "GAME_DATE": "DEC 27, 1993", "MATCHUP": "UTH vs. MIN", "WL": "W", "MIN": 240, "FGM": 35, "FGA": 86, "FG_PCT": 0.407, "FG3M": 0, "FG3A": 6, "FG3_PCT": 0.0, "FTM": 27, "FTA": 36, "FT_PCT": 0.75, "OREB": 17, "DREB": 26, "REB": 43, "AST": 24, "STL": 11, "BLK": 6, "TOV": 8, "PF": 23, "PTS": 97}, {"Team_ID": 1610612762, "Game_ID": "0029300318", "GAME_DATE": "DEC 23, 1993", "MATCHUP": "UTH @ SAN", "WL": "W", "MIN": 240, "FGM": 40, "FGA": 77, "FG_PCT": 0.519, "FG3M": 2, "FG3A": 3, "FG3_PCT": 0.6666666666666666, "FTM": 14, "FTA": 18, "FT_PCT": 0.778, "OREB": 8, "DREB": 23, "REB": 31, "AST": 24, "STL": 5, "BLK": 6, "TOV": 11, "PF": 18, "PTS": 96}, {"Team_ID": 1610612762, "Game_ID": "0029300304", "GAME_DATE": "DEC 21, 1993", "MATCHUP": "UTH @ CLE", "WL": "L", "MIN": 240, "FGM": 38, "FGA": 71, "FG_PCT": 0.535, "FG3M": 2, "FG3A": 5, "FG3_PCT": 0.4, "FTM": 19, "FTA": 23, "FT_PCT": 0.826, "OREB": 7, "DREB": 24, "REB": 31, "AST": 32, "STL": 8, "BLK": 6, "TOV": 17, "PF": 20, "PTS": 97}, {"Team_ID": 1610612762, "Game_ID": "0029300289", "GAME_DATE": "DEC 18, 1993", "MATCHUP": "UTH @ WAS", "WL": "W", "MIN": 240, "FGM": 40, "FGA": 88, "FG_PCT": 0.455, "FG3M": 0, "FG3A": 3, "FG3_PCT": 0.0, "FTM": 22, "FTA": 26, "FT_PCT": 0.846, "OREB": 13, "DREB": 26, "REB": 39, "AST": 25, "STL": 13, "BLK": 2, "TOV": 14, "PF": 29, "PTS": 102}, {"Team_ID": 1610612762, "Game_ID": "0029300281", "GAME_DATE": "DEC 17, 1993", "MATCHUP": "UTH @ BOS", "WL": "W", "MIN": 240, "FGM": 39, "FGA": 83, "FG_PCT": 0.47, "FG3M": 2, "FG3A": 8, "FG3_PCT": 0.25, "FTM": 17, "FTA": 27, "FT_PCT": 0.63, "OREB": 11, "DREB": 37, "REB": 48, "AST": 26, "STL": 6, "BLK": 3, "TOV": 16, "PF": 21, "PTS": 97}, {"Team_ID": 1610612762, "Game_ID": "0029300265", "GAME_DATE": "DEC 15, 1993", "MATCHUP": "UTH @ MIN", "WL": "W", "MIN": 240, "FGM": 37, "FGA": 81, "FG_PCT": 0.457, "FG3M": 0, "FG3A": 4, "FG3_PCT": 0.0, "FTM": 23, "FTA": 31, "FT_PCT": 0.742, "OREB": 4, "DREB": 32, "REB": 36, "AST": 31, "STL": 5, "BLK": 7, "TOV": 15, "PF": 15, "PTS": 97}, {"Team_ID": 1610612762, "Game_ID": "0029300253", "GAME_DATE": "DEC 13, 1993", "MATCHUP": "UTH vs. SAN", "WL": "W", "MIN": 240, "FGM": 42, "FGA": 86, "FG_PCT": 0.488, "FG3M": 1, "FG3A": 6, "FG3_PCT": 0.16666666666666666, "FTM": 17, "FTA": 23, "FT_PCT": 0.739, "OREB": 13, "DREB": 22, "REB": 35, "AST": 29, "STL": 9, "BLK": 2, "TOV": 7, "PF": 24, "PTS": 102}, {"Team_ID": 1610612762, "Game_ID": "0029300240", "GAME_DATE": "DEC 11, 1993", "MATCHUP": "UTH @ GOS", "WL": "L", "MIN": 265, "FGM": 47, "FGA": 96, "FG_PCT": 0.49, "FG3M": 6, "FG3A": 12, "FG3_PCT": 0.5, "FTM": 12, "FTA": 19, "FT_PCT": 0.632, "OREB": 15, "DREB": 27, "REB": 42, "AST": 36, "STL": 11, "BLK": 1, "TOV": 16, "PF": 29, "PTS": 112}, {"Team_ID": 1610612762, "Game_ID": "0029300232", "GAME_DATE": "DEC 10, 1993", "MATCHUP": "UTH @ DEN", "WL": "L", "MIN": 240, "FGM": 37, "FGA": 94, "FG_PCT": 0.394, "FG3M": 3, "FG3A": 9, "FG3_PCT": 0.3333333333333333, "FTM": 21, "FTA": 25, "FT_PCT": 0.84, "OREB": 17, "DREB": 27, "REB": 44, "AST": 20, "STL": 10, "BLK": 7, "TOV": 15, "PF": 27, "PTS": 98}, {"Team_ID": 1610612762, "Game_ID": "0029300216", "GAME_DATE": "DEC 08, 1993", "MATCHUP": "UTH vs. WAS", "WL": "W", "MIN": 240, "FGM": 46, "FGA": 84, "FG_PCT": 0.548, "FG3M": 1, "FG3A": 4, "FG3_PCT": 0.25, "FTM": 20, "FTA": 24, "FT_PCT": 0.833, "OREB": 11, "DREB": 30, "REB": 41, "AST": 33, "STL": 10, "BLK": 3, "TOV": 14, "PF": 25, "PTS": 113}, {"Team_ID": 1610612762, "Game_ID": "0029300206", "GAME_DATE": "DEC 06, 1993", "MATCHUP": "UTH vs. NYK", "WL": "W", "MIN": 240, "FGM": 38, "FGA": 78, "FG_PCT": 0.487, "FG3M": 1, "FG3A": 4, "FG3_PCT": 0.25, "FTM": 26, "FTA": 39, "FT_PCT": 0.667, "OREB": 12, "DREB": 28, "REB": 40, "AST": 25, "STL": 10, "BLK": 4, "TOV": 11, "PF": 22, "PTS": 103}, {"Team_ID": 1610612762, "Game_ID": "0029300194", "GAME_DATE": "DEC 04, 1993", "MATCHUP": "UTH vs. CHH", "WL": "W", "MIN": 240, "FGM": 49, "FGA": 95, "FG_PCT": 0.516, "FG3M": 4, "FG3A": 7, "FG3_PCT": 0.5714285714285714, "FTM": 20, "FTA": 30, "FT_PCT": 0.667, "OREB": 19, "DREB": 27, "REB": 46, "AST": 30, "STL": 11, "BLK": 4, "TOV": 12, "PF": 23, "PTS": 122}, {"Team_ID": 1610612762, "Game_ID": "0029300182", "GAME_DATE": "DEC 02, 1993", "MATCHUP": "UTH vs. IND", "WL": "W", "MIN": 240, "FGM": 35, "FGA": 79, "FG_PCT": 0.443, "FG3M": 1, "FG3A": 5, "FG3_PCT": 0.2, "FTM": 32, "FTA": 43, "FT_PCT": 0.744, "OREB": 19, "DREB": 29, "REB": 48, "AST": 26, "STL": 13, "BLK": 3, "TOV": 16, "PF": 30, "PTS": 103}, {"Team_ID": 1610612762, "Game_ID": "0029300168", "GAME_DATE": "NOV 30, 1993", "MATCHUP": "UTH vs. DEN", "WL": "W", "MIN": 240, "FGM": 39, "FGA": 90, "FG_PCT": 0.433, "FG3M": 0, "FG3A": 2, "FG3_PCT": 0.0, "FTM": 25, "FTA": 31, "FT_PCT": 0.806, "OREB": 14, "DREB": 30, "REB": 44, "AST": 24, "STL": 11, "BLK": 7, "TOV": 16, "PF": 25, "PTS": 103}, {"Team_ID": 1610612762, "Game_ID": "0029300158", "GAME_DATE": "NOV 27, 1993", "MATCHUP": "UTH @ PHX", "WL": "L", "MIN": 240, "FGM": 39, "FGA": 89, "FG_PCT": 0.438, "FG3M": 5, "FG3A": 15, "FG3_PCT": 0.3333333333333333, "FTM": 15, "FTA": 17, "FT_PCT": 0.882, "OREB": 12, "DREB": 23, "REB": 35, "AST": 26, "STL": 8, "BLK": 3, "TOV": 18, "PF": 29, "PTS": 98}, {"Team_ID": 1610612762, "Game_ID": "0029300140", "GAME_DATE": "NOV 26, 1993", "MATCHUP": "UTH vs. NJN", "WL": "W", "MIN": 240, "FGM": 38, "FGA": 73, "FG_PCT": 0.521, "FG3M": 1, "FG3A": 4, "FG3_PCT": 0.25, "FTM": 23, "FTA": 30, "FT_PCT": 0.767, "OREB": 6, "DREB": 35, "REB": 41, "AST": 25, "STL": 11, "BLK": 7, "TOV": 15, "PF": 29, "PTS": 100}, {"Team_ID": 1610612762, "Game_ID": "0029300129", "GAME_DATE": "NOV 24, 1993", "MATCHUP": "UTH vs. HOU", "WL": "L", "MIN": 265, "FGM": 36, "FGA": 84, "FG_PCT": 0.429, "FG3M": 5, "FG3A": 10, "FG3_PCT": 0.5, "FTM": 16, "FTA": 28, "FT_PCT": 0.571, "OREB": 10, "DREB": 37, "REB": 47, "AST": 20, "STL": 9, "BLK": 2, "TOV": 15, "PF": 24, "PTS": 93}, {"Team_ID": 1610612762, "Game_ID": "0029300113", "GAME_DATE": "NOV 20, 1993", "MATCHUP": "UTH @ NYK", "WL": "W", "MIN": 240, "FGM": 30, "FGA": 70, "FG_PCT": 0.429, "FG3M": 2, "FG3A": 4, "FG3_PCT": 0.5, "FTM": 24, "FTA": 30, "FT_PCT": 0.8, "OREB": 14, "DREB": 34, "REB": 48, "AST": 23, "STL": 6, "BLK": 2, "TOV": 19, "PF": 26, "PTS": 86}, {"Team_ID": 1610612762, "Game_ID": "0029300099", "GAME_DATE": "NOV 19, 1993", "MATCHUP": "UTH @ PHL", "WL": "L", "MIN": 240, "FGM": 48, "FGA": 91, "FG_PCT": 0.527, "FG3M": 2, "FG3A": 6, "FG3_PCT": 0.3333333333333333, "FTM": 17, "FTA": 22, "FT_PCT": 0.773, "OREB": 10, "DREB": 23, "REB": 33, "AST": 36, "STL": 11, "BLK": 3, "TOV": 8, "PF": 23, "PTS": 115}, {"Team_ID": 1610612762, "Game_ID": "0029300085", "GAME_DATE": "NOV 17, 1993", "MATCHUP": "UTH @ MIA", "WL": "W", "MIN": 240, "FGM": 39, "FGA": 76, "FG_PCT": 0.513, "FG3M": 1, "FG3A": 9, "FG3_PCT": 0.1111111111111111, "FTM": 36, "FTA": 44, "FT_PCT": 0.818, "OREB": 12, "DREB": 24, "REB": 36, "AST": 27, "STL": 8, "BLK": 4, "TOV": 10, "PF": 27, "PTS": 115}, {"Team_ID": 1610612762, "Game_ID": "0029300077", "GAME_DATE": "NOV 16, 1993", "MATCHUP": "UTH @ ORL", "WL": "L", "MIN": 240, "FGM": 32, "FGA": 84, "FG_PCT": 0.381, "FG3M": 3, "FG3A": 12, "FG3_PCT": 0.25, "FTM": 29, "FTA": 36, "FT_PCT": 0.806, "OREB": 10, "DREB": 19, "REB": 29, "AST": 23, "STL": 8, "BLK": 2, "TOV": 13, "PF": 23, "PTS": 96}, {"Team_ID": 1610612762, "Game_ID": "0029300067", "GAME_DATE": "NOV 13, 1993", "MATCHUP": "UTH @ DAL", "WL": "W", "MIN": 240, "FGM": 40, "FGA": 72, "FG_PCT": 0.556, "FG3M": 0, "FG3A": 1, "FG3_PCT": 0.0, "FTM": 21, "FTA": 26, "FT_PCT": 0.808, "OREB": 10, "DREB": 18, "REB": 28, "AST": 24, "STL": 11, "BLK": 4, "TOV": 15, "PF": 26, "PTS": 101}, {"Team_ID": 1610612762, "Game_ID": "0029300058", "GAME_DATE": "NOV 12, 1993", "MATCHUP": "UTH vs. DET", "WL": "W", "MIN": 240, "FGM": 43, "FGA": 86, "FG_PCT": 0.5, "FG3M": 2, "FG3A": 7, "FG3_PCT": 0.2857142857142857, "FTM": 21, "FTA": 27, "FT_PCT": 0.778, "OREB": 13, "DREB": 29, "REB": 42, "AST": 29, "STL": 7, "BLK": 7, "TOV": 9, "PF": 28, "PTS": 109}, {"Team_ID": 1610612762, "Game_ID": "0029300040", "GAME_DATE": "NOV 10, 1993", "MATCHUP": "UTH vs. ATL", "WL": "W", "MIN": 240, "FGM": 35, "FGA": 92, "FG_PCT": 0.38, "FG3M": 2, "FG3A": 7, "FG3_PCT": 0.2857142857142857, "FTM": 19, "FTA": 30, "FT_PCT": 0.633, "OREB": 31, "DREB": 24, "REB": 55, "AST": 22, "STL": 12, "BLK": 4, "TOV": 15, "PF": 18, "PTS": 91}, {"Team_ID": 1610612762, "Game_ID": "0029300029", "GAME_DATE": "NOV 08, 1993", "MATCHUP": "UTH vs. SEA", "WL": "L", "MIN": 240, "FGM": 35, "FGA": 77, "FG_PCT": 0.455, "FG3M": 4, "FG3A": 9, "FG3_PCT": 0.4444444444444444, "FTM": 26, "FTA": 36, "FT_PCT": 0.722, "OREB": 20, "DREB": 21, "REB": 41, "AST": 20, "STL": 9, "BLK": 6, "TOV": 17, "PF": 26, "PTS": 100}, {"Team_ID": 1610612762, "Game_ID": "0029300014", "GAME_DATE": "NOV 06, 1993", "MATCHUP": "UTH @ MIN", "WL": "W", "MIN": 240, "FGM": 37, "FGA": 85, "FG_PCT": 0.435, "FG3M": 1, "FG3A": 6, "FG3_PCT": 0.16666666666666666, "FTM": 30, "FTA": 40, "FT_PCT": 0.75, "OREB": 9, "DREB": 29, "REB": 38, "AST": 29, "STL": 13, "BLK": 8, "TOV": 13, "PF": 28, "PTS": 105}, {"Team_ID": 1610612762, "Game_ID": "0029300004", "GAME_DATE": "NOV 05, 1993", "MATCHUP": "UTH vs. DAL", "WL": "W", "MIN": 240, "FGM": 39, "FGA": 77, "FG_PCT": 0.506, "FG3M": 4, "FG3A": 7, "FG3_PCT": 0.5714285714285714, "FTM": 20, "FTA": 27, "FT_PCT": 0.741, "OREB": 13, "DREB": 25, "REB": 38, "AST": 24, "STL": 7, "BLK": 4, "TOV": 14, "PF": 19, "PTS": 102}]