[{"Team_ID": 1610612750, "Game_ID": "0020301183", "GAME_DATE": "APR 14, 2004", "MATCHUP": "MIN @ MEM", "WL": "W", "MIN": 240, "FGM": 39, "FGA": 72, "FG_PCT": 0.542, "FG3M": 7, "FG3A": 12, "FG3_PCT": 0.5833333333333334, "FTM": 22, "FTA": 26, "FT_PCT": 0.846, "OREB": 10, "DREB": 32, "REB": 42, "AST": 23, "STL": 8, "BLK": 6, "TOV": 14, "PF": 24, "PTS": 107}, {"Team_ID": 1610612750, "Game_ID": "0020301167", "GAME_DATE": "APR 12, 2004", "MATCHUP": "MIN vs. UTA", "WL": "W", "MIN": 240, "FGM": 30, "FGA": 62, "FG_PCT": 0.484, "FG3M": 4, "FG3A": 11, "FG3_PCT": 0.36363636363636365, "FTM": 40, "FTA": 49, "FT_PCT": 0.816, "OREB": 10, "DREB": 32, "REB": 42, "AST": 15, "STL": 4, "BLK": 10, "TOV": 10, "PF": 24, "PTS": 104}, {"Team_ID": 1610612750, "Game_ID": "0020301146", "GAME_DATE": "APR 09, 2004", "MATCHUP": "MIN @ GSW", "WL": "W", "MIN": 240, "FGM": 36, "FGA": 85, "FG_PCT": 0.424, "FG3M": 3, "FG3A": 12, "FG3_PCT": 0.25, "FTM": 17, "FTA": 22, "FT_PCT": 0.773, "OREB": 13, "DREB": 32, "REB": 45, "AST": 20, "STL": 10, "BLK": 6, "TOV": 13, "PF": 24, "PTS": 92}, {"Team_ID": 1610612750, "Game_ID": "0020301135", "GAME_DATE": "APR 08, 2004", "MATCHUP": "MIN @ SAC", "WL": "W", "MIN": 240, "FGM": 39, "FGA": 85, "FG_PCT": 0.459, "FG3M": 3, "FG3A": 11, "FG3_PCT": 0.2727272727272727, "FTM": 13, "FTA": 20, "FT_PCT": 0.65, "OREB": 13, "DREB": 35, "REB": 48, "AST": 12, "STL": 7, "BLK": 5, "TOV": 11, "PF": 20, "PTS": 94}, {"Team_ID": 1610612750, "Game_ID": "0020301109", "GAME_DATE": "APR 04, 2004", "MATCHUP": "MIN vs. MEM", "WL": "W", "MIN": 240, "FGM": 32, "FGA": 81, "FG_PCT": 0.395, "FG3M": 7, "FG3A": 13, "FG3_PCT": 0.5384615384615384, "FTM": 19, "FTA": 24, "FT_PCT": 0.792, "OREB": 19, "DREB": 35, "REB": 54, "AST": 17, "STL": 6, "BLK": 6, "TOV": 11, "PF": 19, "PTS": 90}, {"Team_ID": 1610612750, "Game_ID": "0020301094", "GAME_DATE": "APR 02, 2004", "MATCHUP": "MIN vs. WAS", "WL": "W", "MIN": 240, "FGM": 39, "FGA": 89, "FG_PCT": 0.438, "FG3M": 5, "FG3A": 18, "FG3_PCT": 0.2777777777777778, "FTM": 8, "FTA": 9, "FT_PCT": 0.889, "OREB": 17, "DREB": 29, "REB": 46, "AST": 29, "STL": 9, "BLK": 5, "TOV": 9, "PF": 18, "PTS": 91}, {"Team_ID": 1610612750, "Game_ID": "0020301083", "GAME_DATE": "MAR 31, 2004", "MATCHUP": "MIN vs. SEA", "WL": "W", "MIN": 240, "FGM": 31, "FGA": 67, "FG_PCT": 0.463, "FG3M": 7, "FG3A": 15, "FG3_PCT": 0.4666666666666667, "FTM": 21, "FTA": 31, "FT_PCT": 0.677, "OREB": 12, "DREB": 35, "REB": 47, "AST": 23, "STL": 5, "BLK": 5, "TOV": 16, "PF": 19, "PTS": 90}, {"Team_ID": 1610612750, "Game_ID": "0020301068", "GAME_DATE": "MAR 29, 2004", "MATCHUP": "MIN @ HOU", "WL": "W", "MIN": 240, "FGM": 34, "FGA": 80, "FG_PCT": 0.425, "FG3M": 5, "FG3A": 11, "FG3_PCT": 0.45454545454545453, "FTM": 21, "FTA": 22, "FT_PCT": 0.955, "OREB": 9, "DREB": 27, "REB": 36, "AST": 25, "STL": 9, "BLK": 10, "TOV": 11, "PF": 19, "PTS": 94}, {"Team_ID": 1610612750, "Game_ID": "0020301055", "GAME_DATE": "MAR 27, 2004", "MATCHUP": "MIN @ LAC", "WL": "W", "MIN": 240, "FGM": 39, "FGA": 85, "FG_PCT": 0.459, "FG3M": 7, "FG3A": 17, "FG3_PCT": 0.4117647058823529, "FTM": 13, "FTA": 14, "FT_PCT": 0.929, "OREB": 9, "DREB": 30, "REB": 39, "AST": 24, "STL": 9, "BLK": 3, "TOV": 9, "PF": 25, "PTS": 98}, {"Team_ID": 1610612750, "Game_ID": "0020301046", "GAME_DATE": "MAR 26, 2004", "MATCHUP": "MIN @ LAL", "WL": "L", "MIN": 240, "FGM": 27, "FGA": 86, "FG_PCT": 0.314, "FG3M": 6, "FG3A": 16, "FG3_PCT": 0.375, "FTM": 13, "FTA": 20, "FT_PCT": 0.65, "OREB": 14, "DREB": 34, "REB": 48, "AST": 19, "STL": 11, "BLK": 3, "TOV": 21, "PF": 25, "PTS": 73}, {"Team_ID": 1610612750, "Game_ID": "0020301030", "GAME_DATE": "MAR 24, 2004", "MATCHUP": "MIN @ DEN", "WL": "L", "MIN": 240, "FGM": 35, "FGA": 75, "FG_PCT": 0.467, "FG3M": 5, "FG3A": 13, "FG3_PCT": 0.38461538461538464, "FTM": 17, "FTA": 21, "FT_PCT": 0.81, "OREB": 10, "DREB": 38, "REB": 48, "AST": 21, "STL": 1, "BLK": 5, "TOV": 21, "PF": 32, "PTS": 92}, {"Team_ID": 1610612750, "Game_ID": "0020301020", "GAME_DATE": "MAR 23, 2004", "MATCHUP": "MIN vs. SAS", "WL": "W", "MIN": 240, "FGM": 32, "FGA": 75, "FG_PCT": 0.427, "FG3M": 0, "FG3A": 4, "FG3_PCT": 0.0, "FTM": 22, "FTA": 28, "FT_PCT": 0.786, "OREB": 6, "DREB": 34, "REB": 40, "AST": 19, "STL": 8, "BLK": 8, "TOV": 10, "PF": 19, "PTS": 86}, {"Team_ID": 1610612750, "Game_ID": "0020301005", "GAME_DATE": "MAR 21, 2004", "MATCHUP": "MIN vs. DEN", "WL": "W", "MIN": 240, "FGM": 38, "FGA": 79, "FG_PCT": 0.481, "FG3M": 5, "FG3A": 10, "FG3_PCT": 0.5, "FTM": 17, "FTA": 22, "FT_PCT": 0.773, "OREB": 9, "DREB": 41, "REB": 50, "AST": 24, "STL": 6, "BLK": 4, "TOV": 12, "PF": 22, "PTS": 98}, {"Team_ID": 1610612750, "Game_ID": "0020300994", "GAME_DATE": "MAR 19, 2004", "MATCHUP": "MIN @ PHX", "WL": "W", "MIN": 240, "FGM": 37, "FGA": 82, "FG_PCT": 0.451, "FG3M": 8, "FG3A": 14, "FG3_PCT": 0.5714285714285714, "FTM": 11, "FTA": 14, "FT_PCT": 0.786, "OREB": 14, "DREB": 36, "REB": 50, "AST": 21, "STL": 7, "BLK": 8, "TOV": 16, "PF": 18, "PTS": 93}, {"Team_ID": 1610612750, "Game_ID": "0020300985", "GAME_DATE": "MAR 18, 2004", "MATCHUP": "MIN @ SAS", "WL": "L", "MIN": 240, "FGM": 31, "FGA": 71, "FG_PCT": 0.437, "FG3M": 2, "FG3A": 9, "FG3_PCT": 0.2222222222222222, "FTM": 22, "FTA": 26, "FT_PCT": 0.846, "OREB": 5, "DREB": 32, "REB": 37, "AST": 15, "STL": 0, "BLK": 0, "TOV": 14, "PF": 29, "PTS": 86}, {"Team_ID": 1610612750, "Game_ID": "0020300959", "GAME_DATE": "MAR 14, 2004", "MATCHUP": "MIN vs. POR", "WL": "L", "MIN": 240, "FGM": 36, "FGA": 90, "FG_PCT": 0.4, "FG3M": 2, "FG3A": 14, "FG3_PCT": 0.14285714285714285, "FTM": 9, "FTA": 14, "FT_PCT": 0.643, "OREB": 20, "DREB": 23, "REB": 43, "AST": 25, "STL": 5, "BLK": 5, "TOV": 6, "PF": 28, "PTS": 83}, {"Team_ID": 1610612750, "Game_ID": "0020300943", "GAME_DATE": "MAR 12, 2004", "MATCHUP": "MIN vs. LAL", "WL": "W", "MIN": 240, "FGM": 36, "FGA": 80, "FG_PCT": 0.45, "FG3M": 4, "FG3A": 10, "FG3_PCT": 0.4, "FTM": 20, "FTA": 25, "FT_PCT": 0.8, "OREB": 9, "DREB": 35, "REB": 44, "AST": 18, "STL": 7, "BLK": 4, "TOV": 12, "PF": 28, "PTS": 96}, {"Team_ID": 1610612750, "Game_ID": "0020300935", "GAME_DATE": "MAR 10, 2004", "MATCHUP": "MIN @ POR", "WL": "L", "MIN": 240, "FGM": 33, "FGA": 84, "FG_PCT": 0.393, "FG3M": 5, "FG3A": 13, "FG3_PCT": 0.38461538461538464, "FTM": 8, "FTA": 9, "FT_PCT": 0.889, "OREB": 18, "DREB": 25, "REB": 43, "AST": 23, "STL": 12, "BLK": 5, "TOV": 13, "PF": 12, "PTS": 79}, {"Team_ID": 1610612750, "Game_ID": "0020300925", "GAME_DATE": "MAR 09, 2004", "MATCHUP": "MIN @ SEA", "WL": "W", "MIN": 240, "FGM": 41, "FGA": 83, "FG_PCT": 0.494, "FG3M": 5, "FG3A": 15, "FG3_PCT": 0.3333333333333333, "FTM": 18, "FTA": 24, "FT_PCT": 0.75, "OREB": 15, "DREB": 30, "REB": 45, "AST": 18, "STL": 4, "BLK": 6, "TOV": 10, "PF": 17, "PTS": 105}, {"Team_ID": 1610612750, "Game_ID": "0020300908", "GAME_DATE": "MAR 07, 2004", "MATCHUP": "MIN vs. BOS", "WL": "L", "MIN": 240, "FGM": 33, "FGA": 92, "FG_PCT": 0.359, "FG3M": 2, "FG3A": 12, "FG3_PCT": 0.16666666666666666, "FTM": 9, "FTA": 10, "FT_PCT": 0.9, "OREB": 12, "DREB": 45, "REB": 57, "AST": 24, "STL": 6, "BLK": 7, "TOV": 12, "PF": 22, "PTS": 77}, {"Team_ID": 1610612750, "Game_ID": "0020300891", "GAME_DATE": "MAR 05, 2004", "MATCHUP": "MIN vs. HOU", "WL": "L", "MIN": 240, "FGM": 43, "FGA": 78, "FG_PCT": 0.551, "FG3M": 5, "FG3A": 12, "FG3_PCT": 0.4166666666666667, "FTM": 18, "FTA": 26, "FT_PCT": 0.692, "OREB": 8, "DREB": 28, "REB": 36, "AST": 30, "STL": 8, "BLK": 3, "TOV": 10, "PF": 21, "PTS": 109}, {"Team_ID": 1610612750, "Game_ID": "0020300879", "GAME_DATE": "MAR 03, 2004", "MATCHUP": "MIN vs. DAL", "WL": "W", "MIN": 240, "FGM": 48, "FGA": 87, "FG_PCT": 0.552, "FG3M": 11, "FG3A": 21, "FG3_PCT": 0.5238095238095238, "FTM": 14, "FTA": 18, "FT_PCT": 0.778, "OREB": 9, "DREB": 43, "REB": 52, "AST": 33, "STL": 4, "BLK": 5, "TOV": 9, "PF": 15, "PTS": 121}, {"Team_ID": 1610612750, "Game_ID": "0020300859", "GAME_DATE": "FEB 29, 2004", "MATCHUP": "MIN @ PHI", "WL": "L", "MIN": 240, "FGM": 28, "FGA": 78, "FG_PCT": 0.359, "FG3M": 2, "FG3A": 9, "FG3_PCT": 0.2222222222222222, "FTM": 16, "FTA": 19, "FT_PCT": 0.842, "OREB": 15, "DREB": 33, "REB": 48, "AST": 16, "STL": 3, "BLK": 5, "TOV": 14, "PF": 18, "PTS": 74}, {"Team_ID": 1610612750, "Game_ID": "0020300841", "GAME_DATE": "FEB 27, 2004", "MATCHUP": "MIN vs. GSW", "WL": "W", "MIN": 240, "FGM": 38, "FGA": 78, "FG_PCT": 0.487, "FG3M": 6, "FG3A": 15, "FG3_PCT": 0.4, "FTM": 9, "FTA": 15, "FT_PCT": 0.6, "OREB": 10, "DREB": 32, "REB": 42, "AST": 35, "STL": 8, "BLK": 8, "TOV": 8, "PF": 14, "PTS": 91}, {"Team_ID": 1610612750, "Game_ID": "0020300827", "GAME_DATE": "FEB 25, 2004", "MATCHUP": "MIN vs. NJN", "WL": "W", "MIN": 240, "FGM": 30, "FGA": 68, "FG_PCT": 0.441, "FG3M": 7, "FG3A": 13, "FG3_PCT": 0.5384615384615384, "FTM": 14, "FTA": 17, "FT_PCT": 0.824, "OREB": 3, "DREB": 42, "REB": 45, "AST": 18, "STL": 5, "BLK": 4, "TOV": 12, "PF": 10, "PTS": 81}, {"Team_ID": 1610612750, "Game_ID": "0020300819", "GAME_DATE": "FEB 24, 2004", "MATCHUP": "MIN @ MIL", "WL": "W", "MIN": 240, "FGM": 42, "FGA": 76, "FG_PCT": 0.553, "FG3M": 2, "FG3A": 9, "FG3_PCT": 0.2222222222222222, "FTM": 22, "FTA": 33, "FT_PCT": 0.667, "OREB": 6, "DREB": 30, "REB": 36, "AST": 20, "STL": 10, "BLK": 3, "TOV": 10, "PF": 22, "PTS": 108}, {"Team_ID": 1610612750, "Game_ID": "0020300805", "GAME_DATE": "FEB 22, 2004", "MATCHUP": "MIN vs. SAS", "WL": "L", "MIN": 240, "FGM": 37, "FGA": 76, "FG_PCT": 0.487, "FG3M": 4, "FG3A": 8, "FG3_PCT": 0.5, "FTM": 14, "FTA": 21, "FT_PCT": 0.667, "OREB": 7, "DREB": 35, "REB": 42, "AST": 25, "STL": 5, "BLK": 7, "TOV": 15, "PF": 22, "PTS": 92}, {"Team_ID": 1610612750, "Game_ID": "0020300790", "GAME_DATE": "FEB 20, 2004", "MATCHUP": "MIN @ DET", "WL": "W", "MIN": 240, "FGM": 34, "FGA": 77, "FG_PCT": 0.442, "FG3M": 4, "FG3A": 10, "FG3_PCT": 0.4, "FTM": 16, "FTA": 25, "FT_PCT": 0.64, "OREB": 8, "DREB": 29, "REB": 37, "AST": 21, "STL": 11, "BLK": 7, "TOV": 9, "PF": 22, "PTS": 88}, {"Team_ID": 1610612750, "Game_ID": "0020300781", "GAME_DATE": "FEB 19, 2004", "MATCHUP": "MIN vs. SAC", "WL": "W", "MIN": 240, "FGM": 35, "FGA": 77, "FG_PCT": 0.455, "FG3M": 3, "FG3A": 10, "FG3_PCT": 0.3, "FTM": 19, "FTA": 24, "FT_PCT": 0.792, "OREB": 14, "DREB": 46, "REB": 60, "AST": 21, "STL": 2, "BLK": 4, "TOV": 16, "PF": 22, "PTS": 92}, {"Team_ID": 1610612750, "Game_ID": "0020300766", "GAME_DATE": "FEB 17, 2004", "MATCHUP": "MIN vs. PHX", "WL": "W", "MIN": 240, "FGM": 38, "FGA": 77, "FG_PCT": 0.494, "FG3M": 3, "FG3A": 8, "FG3_PCT": 0.375, "FTM": 31, "FTA": 33, "FT_PCT": 0.939, "OREB": 12, "DREB": 32, "REB": 44, "AST": 26, "STL": 11, "BLK": 5, "TOV": 14, "PF": 22, "PTS": 110}, {"Team_ID": 1610612750, "Game_ID": "0020300757", "GAME_DATE": "FEB 11, 2004", "MATCHUP": "MIN @ UTA", "WL": "W", "MIN": 240, "FGM": 26, "FGA": 68, "FG_PCT": 0.382, "FG3M": 3, "FG3A": 4, "FG3_PCT": 0.75, "FTM": 22, "FTA": 28, "FT_PCT": 0.786, "OREB": 8, "DREB": 31, "REB": 39, "AST": 14, "STL": 10, "BLK": 8, "TOV": 15, "PF": 16, "PTS": 77}, {"Team_ID": 1610612750, "Game_ID": "0020300744", "GAME_DATE": "FEB 10, 2004", "MATCHUP": "MIN vs. LAC", "WL": "W", "MIN": 240, "FGM": 41, "FGA": 85, "FG_PCT": 0.482, "FG3M": 3, "FG3A": 7, "FG3_PCT": 0.42857142857142855, "FTM": 11, "FTA": 15, "FT_PCT": 0.733, "OREB": 12, "DREB": 34, "REB": 46, "AST": 29, "STL": 7, "BLK": 5, "TOV": 9, "PF": 22, "PTS": 96}, {"Team_ID": 1610612750, "Game_ID": "0020300731", "GAME_DATE": "FEB 08, 2004", "MATCHUP": "MIN vs. MEM", "WL": "L", "MIN": 240, "FGM": 39, "FGA": 77, "FG_PCT": 0.506, "FG3M": 3, "FG3A": 6, "FG3_PCT": 0.5, "FTM": 17, "FTA": 21, "FT_PCT": 0.81, "OREB": 10, "DREB": 30, "REB": 40, "AST": 24, "STL": 9, "BLK": 6, "TOV": 18, "PF": 19, "PTS": 98}, {"Team_ID": 1610612750, "Game_ID": "0020300715", "GAME_DATE": "FEB 06, 2004", "MATCHUP": "MIN vs. CLE", "WL": "W", "MIN": 240, "FGM": 41, "FGA": 84, "FG_PCT": 0.488, "FG3M": 3, "FG3A": 5, "FG3_PCT": 0.6, "FTM": 18, "FTA": 22, "FT_PCT": 0.818, "OREB": 13, "DREB": 23, "REB": 36, "AST": 28, "STL": 7, "BLK": 4, "TOV": 8, "PF": 21, "PTS": 103}, {"Team_ID": 1610612750, "Game_ID": "0020300702", "GAME_DATE": "FEB 04, 2004", "MATCHUP": "MIN @ ATL", "WL": "L", "MIN": 240, "FGM": 33, "FGA": 86, "FG_PCT": 0.384, "FG3M": 5, "FG3A": 10, "FG3_PCT": 0.5, "FTM": 18, "FTA": 20, "FT_PCT": 0.9, "OREB": 12, "DREB": 29, "REB": 41, "AST": 18, "STL": 7, "BLK": 2, "TOV": 9, "PF": 21, "PTS": 89}, {"Team_ID": 1610612750, "Game_ID": "0020300695", "GAME_DATE": "FEB 03, 2004", "MATCHUP": "MIN vs. ORL", "WL": "W", "MIN": 240, "FGM": 44, "FGA": 80, "FG_PCT": 0.55, "FG3M": 5, "FG3A": 10, "FG3_PCT": 0.5, "FTM": 20, "FTA": 23, "FT_PCT": 0.87, "OREB": 10, "DREB": 37, "REB": 47, "AST": 35, "STL": 4, "BLK": 9, "TOV": 12, "PF": 19, "PTS": 113}, {"Team_ID": 1610612750, "Game_ID": "0020300682", "GAME_DATE": "FEB 01, 2004", "MATCHUP": "MIN vs. PHI", "WL": "W", "MIN": 240, "FGM": 40, "FGA": 81, "FG_PCT": 0.494, "FG3M": 4, "FG3A": 16, "FG3_PCT": 0.25, "FTM": 22, "FTA": 22, "FT_PCT": 1.0, "OREB": 7, "DREB": 30, "REB": 37, "AST": 28, "STL": 7, "BLK": 7, "TOV": 11, "PF": 28, "PTS": 106}, {"Team_ID": 1610612750, "Game_ID": "0020300667", "GAME_DATE": "JAN 30, 2004", "MATCHUP": "MIN @ LAL", "WL": "W", "MIN": 240, "FGM": 35, "FGA": 73, "FG_PCT": 0.479, "FG3M": 4, "FG3A": 15, "FG3_PCT": 0.26666666666666666, "FTM": 23, "FTA": 28, "FT_PCT": 0.821, "OREB": 8, "DREB": 33, "REB": 41, "AST": 22, "STL": 7, "BLK": 3, "TOV": 12, "PF": 22, "PTS": 97}, {"Team_ID": 1610612750, "Game_ID": "0020300656", "GAME_DATE": "JAN 28, 2004", "MATCHUP": "MIN @ GSW", "WL": "L", "MIN": 240, "FGM": 34, "FGA": 88, "FG_PCT": 0.386, "FG3M": 4, "FG3A": 11, "FG3_PCT": 0.36363636363636365, "FTM": 18, "FTA": 22, "FT_PCT": 0.818, "OREB": 17, "DREB": 37, "REB": 54, "AST": 25, "STL": 6, "BLK": 10, "TOV": 15, "PF": 28, "PTS": 90}, {"Team_ID": 1610612750, "Game_ID": "0020300638", "GAME_DATE": "JAN 26, 2004", "MATCHUP": "MIN @ DEN", "WL": "W", "MIN": 240, "FGM": 39, "FGA": 93, "FG_PCT": 0.419, "FG3M": 3, "FG3A": 10, "FG3_PCT": 0.3, "FTM": 16, "FTA": 21, "FT_PCT": 0.762, "OREB": 17, "DREB": 28, "REB": 45, "AST": 24, "STL": 11, "BLK": 4, "TOV": 9, "PF": 17, "PTS": 97}, {"Team_ID": 1610612750, "Game_ID": "0020300630", "GAME_DATE": "JAN 25, 2004", "MATCHUP": "MIN vs. PHX", "WL": "W", "MIN": 240, "FGM": 36, "FGA": 82, "FG_PCT": 0.439, "FG3M": 6, "FG3A": 14, "FG3_PCT": 0.42857142857142855, "FTM": 21, "FTA": 28, "FT_PCT": 0.75, "OREB": 11, "DREB": 35, "REB": 46, "AST": 26, "STL": 5, "BLK": 6, "TOV": 10, "PF": 17, "PTS": 99}, {"Team_ID": 1610612750, "Game_ID": "0020300614", "GAME_DATE": "JAN 23, 2004", "MATCHUP": "MIN vs. DET", "WL": "W", "MIN": 240, "FGM": 31, "FGA": 85, "FG_PCT": 0.365, "FG3M": 4, "FG3A": 14, "FG3_PCT": 0.2857142857142857, "FTM": 14, "FTA": 15, "FT_PCT": 0.933, "OREB": 12, "DREB": 35, "REB": 47, "AST": 18, "STL": 9, "BLK": 6, "TOV": 12, "PF": 17, "PTS": 80}, {"Team_ID": 1610612750, "Game_ID": "0020300596", "GAME_DATE": "JAN 21, 2004", "MATCHUP": "MIN @ TOR", "WL": "W", "MIN": 240, "FGM": 41, "FGA": 73, "FG_PCT": 0.562, "FG3M": 4, "FG3A": 8, "FG3_PCT": 0.5, "FTM": 22, "FTA": 28, "FT_PCT": 0.786, "OREB": 12, "DREB": 31, "REB": 43, "AST": 19, "STL": 7, "BLK": 8, "TOV": 17, "PF": 25, "PTS": 108}, {"Team_ID": 1610612750, "Game_ID": "0020300586", "GAME_DATE": "JAN 19, 2004", "MATCHUP": "MIN vs. NOH", "WL": "W", "MIN": 240, "FGM": 40, "FGA": 78, "FG_PCT": 0.513, "FG3M": 1, "FG3A": 9, "FG3_PCT": 0.1111111111111111, "FTM": 16, "FTA": 20, "FT_PCT": 0.8, "OREB": 9, "DREB": 25, "REB": 34, "AST": 23, "STL": 10, "BLK": 1, "TOV": 14, "PF": 23, "PTS": 97}, {"Team_ID": 1610612750, "Game_ID": "0020300566", "GAME_DATE": "JAN 17, 2004", "MATCHUP": "MIN @ HOU", "WL": "L", "MIN": 240, "FGM": 29, "FGA": 79, "FG_PCT": 0.367, "FG3M": 6, "FG3A": 16, "FG3_PCT": 0.375, "FTM": 12, "FTA": 16, "FT_PCT": 0.75, "OREB": 7, "DREB": 21, "REB": 28, "AST": 16, "STL": 7, "BLK": 5, "TOV": 13, "PF": 20, "PTS": 76}, {"Team_ID": 1610612750, "Game_ID": "0020300548", "GAME_DATE": "JAN 14, 2004", "MATCHUP": "MIN @ SAS", "WL": "W", "MIN": 240, "FGM": 39, "FGA": 77, "FG_PCT": 0.506, "FG3M": 3, "FG3A": 6, "FG3_PCT": 0.5, "FTM": 19, "FTA": 25, "FT_PCT": 0.76, "OREB": 8, "DREB": 30, "REB": 38, "AST": 19, "STL": 2, "BLK": 6, "TOV": 9, "PF": 22, "PTS": 100}, {"Team_ID": 1610612750, "Game_ID": "0020300535", "GAME_DATE": "JAN 13, 2004", "MATCHUP": "MIN @ NOH", "WL": "W", "MIN": 240, "FGM": 33, "FGA": 77, "FG_PCT": 0.429, "FG3M": 3, "FG3A": 10, "FG3_PCT": 0.3, "FTM": 25, "FTA": 31, "FT_PCT": 0.806, "OREB": 13, "DREB": 27, "REB": 40, "AST": 18, "STL": 6, "BLK": 4, "TOV": 13, "PF": 20, "PTS": 94}, {"Team_ID": 1610612750, "Game_ID": "0020300519", "GAME_DATE": "JAN 10, 2004", "MATCHUP": "MIN vs. MIA", "WL": "W", "MIN": 240, "FGM": 31, "FGA": 75, "FG_PCT": 0.413, "FG3M": 3, "FG3A": 10, "FG3_PCT": 0.3, "FTM": 18, "FTA": 28, "FT_PCT": 0.643, "OREB": 13, "DREB": 34, "REB": 47, "AST": 19, "STL": 4, "BLK": 8, "TOV": 10, "PF": 18, "PTS": 83}, {"Team_ID": 1610612750, "Game_ID": "0020300504", "GAME_DATE": "JAN 08, 2004", "MATCHUP": "MIN vs. POR", "WL": "W", "MIN": 240, "FGM": 40, "FGA": 82, "FG_PCT": 0.488, "FG3M": 3, "FG3A": 12, "FG3_PCT": 0.25, "FTM": 13, "FTA": 17, "FT_PCT": 0.765, "OREB": 12, "DREB": 35, "REB": 47, "AST": 30, "STL": 7, "BLK": 7, "TOV": 9, "PF": 15, "PTS": 96}, {"Team_ID": 1610612750, "Game_ID": "0020300488", "GAME_DATE": "JAN 06, 2004", "MATCHUP": "MIN vs. LAL", "WL": "W", "MIN": 240, "FGM": 43, "FGA": 79, "FG_PCT": 0.544, "FG3M": 1, "FG3A": 8, "FG3_PCT": 0.125, "FTM": 19, "FTA": 26, "FT_PCT": 0.731, "OREB": 9, "DREB": 38, "REB": 47, "AST": 26, "STL": 4, "BLK": 5, "TOV": 13, "PF": 22, "PTS": 106}, {"Team_ID": 1610612750, "Game_ID": "0020300469", "GAME_DATE": "JAN 03, 2004", "MATCHUP": "MIN @ DAL", "WL": "L", "MIN": 240, "FGM": 43, "FGA": 91, "FG_PCT": 0.473, "FG3M": 9, "FG3A": 20, "FG3_PCT": 0.45, "FTM": 17, "FTA": 22, "FT_PCT": 0.773, "OREB": 17, "DREB": 29, "REB": 46, "AST": 20, "STL": 3, "BLK": 2, "TOV": 11, "PF": 21, "PTS": 112}, {"Team_ID": 1610612750, "Game_ID": "0020300458", "GAME_DATE": "JAN 02, 2004", "MATCHUP": "MIN vs. ATL", "WL": "W", "MIN": 240, "FGM": 38, "FGA": 93, "FG_PCT": 0.409, "FG3M": 4, "FG3A": 13, "FG3_PCT": 0.3076923076923077, "FTM": 13, "FTA": 14, "FT_PCT": 0.929, "OREB": 18, "DREB": 38, "REB": 56, "AST": 32, "STL": 8, "BLK": 7, "TOV": 13, "PF": 18, "PTS": 93}, {"Team_ID": 1610612750, "Game_ID": "0020300442", "GAME_DATE": "DEC 30, 2003", "MATCHUP": "MIN vs. CHI", "WL": "W", "MIN": 240, "FGM": 39, "FGA": 77, "FG_PCT": 0.506, "FG3M": 3, "FG3A": 10, "FG3_PCT": 0.3, "FTM": 17, "FTA": 29, "FT_PCT": 0.586, "OREB": 6, "DREB": 41, "REB": 47, "AST": 28, "STL": 2, "BLK": 4, "TOV": 16, "PF": 21, "PTS": 98}, {"Team_ID": 1610612750, "Game_ID": "0020300422", "GAME_DATE": "DEC 27, 2003", "MATCHUP": "MIN @ SEA", "WL": "W", "MIN": 240, "FGM": 43, "FGA": 82, "FG_PCT": 0.524, "FG3M": 3, "FG3A": 9, "FG3_PCT": 0.3333333333333333, "FTM": 15, "FTA": 18, "FT_PCT": 0.833, "OREB": 13, "DREB": 36, "REB": 49, "AST": 24, "STL": 7, "BLK": 5, "TOV": 17, "PF": 22, "PTS": 104}, {"Team_ID": 1610612750, "Game_ID": "0020300416", "GAME_DATE": "DEC 26, 2003", "MATCHUP": "MIN @ POR", "WL": "L", "MIN": 240, "FGM": 40, "FGA": 87, "FG_PCT": 0.46, "FG3M": 5, "FG3A": 13, "FG3_PCT": 0.38461538461538464, "FTM": 7, "FTA": 11, "FT_PCT": 0.636, "OREB": 12, "DREB": 21, "REB": 33, "AST": 28, "STL": 8, "BLK": 4, "TOV": 10, "PF": 21, "PTS": 92}, {"Team_ID": 1610612750, "Game_ID": "0020300390", "GAME_DATE": "DEC 23, 2003", "MATCHUP": "MIN @ NYK", "WL": "W", "MIN": 240, "FGM": 35, "FGA": 74, "FG_PCT": 0.473, "FG3M": 2, "FG3A": 3, "FG3_PCT": 0.6666666666666666, "FTM": 26, "FTA": 33, "FT_PCT": 0.788, "OREB": 8, "DREB": 27, "REB": 35, "AST": 15, "STL": 10, "BLK": 1, "TOV": 7, "PF": 22, "PTS": 98}, {"Team_ID": 1610612750, "Game_ID": "0020300373", "GAME_DATE": "DEC 20, 2003", "MATCHUP": "MIN vs. IND", "WL": "W", "MIN": 240, "FGM": 36, "FGA": 69, "FG_PCT": 0.522, "FG3M": 3, "FG3A": 6, "FG3_PCT": 0.5, "FTM": 27, "FTA": 32, "FT_PCT": 0.844, "OREB": 5, "DREB": 29, "REB": 34, "AST": 29, "STL": 9, "BLK": 14, "TOV": 13, "PF": 24, "PTS": 102}, {"Team_ID": 1610612750, "Game_ID": "0020300357", "GAME_DATE": "DEC 18, 2003", "MATCHUP": "MIN vs. DAL", "WL": "W", "MIN": 240, "FGM": 42, "FGA": 80, "FG_PCT": 0.525, "FG3M": 3, "FG3A": 11, "FG3_PCT": 0.2727272727272727, "FTM": 27, "FTA": 34, "FT_PCT": 0.794, "OREB": 12, "DREB": 30, "REB": 42, "AST": 34, "STL": 8, "BLK": 2, "TOV": 14, "PF": 23, "PTS": 114}, {"Team_ID": 1610612750, "Game_ID": "0020300341", "GAME_DATE": "DEC 16, 2003", "MATCHUP": "MIN vs. HOU", "WL": "W", "MIN": 240, "FGM": 37, "FGA": 77, "FG_PCT": 0.481, "FG3M": 4, "FG3A": 8, "FG3_PCT": 0.5, "FTM": 14, "FTA": 21, "FT_PCT": 0.667, "OREB": 10, "DREB": 37, "REB": 47, "AST": 26, "STL": 8, "BLK": 8, "TOV": 12, "PF": 21, "PTS": 92}, {"Team_ID": 1610612750, "Game_ID": "0020300333", "GAME_DATE": "DEC 15, 2003", "MATCHUP": "MIN @ BOS", "WL": "W", "MIN": 240, "FGM": 49, "FGA": 78, "FG_PCT": 0.628, "FG3M": 1, "FG3A": 7, "FG3_PCT": 0.14285714285714285, "FTM": 17, "FTA": 20, "FT_PCT": 0.85, "OREB": 5, "DREB": 35, "REB": 40, "AST": 27, "STL": 9, "BLK": 4, "TOV": 13, "PF": 18, "PTS": 116}, {"Team_ID": 1610612750, "Game_ID": "0020300310", "GAME_DATE": "DEC 12, 2003", "MATCHUP": "MIN @ WAS", "WL": "W", "MIN": 240, "FGM": 47, "FGA": 84, "FG_PCT": 0.56, "FG3M": 1, "FG3A": 7, "FG3_PCT": 0.14285714285714285, "FTM": 15, "FTA": 19, "FT_PCT": 0.789, "OREB": 9, "DREB": 32, "REB": 41, "AST": 23, "STL": 8, "BLK": 4, "TOV": 11, "PF": 19, "PTS": 110}, {"Team_ID": 1610612750, "Game_ID": "0020300295", "GAME_DATE": "DEC 09, 2003", "MATCHUP": "MIN vs. GSW", "WL": "L", "MIN": 240, "FGM": 38, "FGA": 81, "FG_PCT": 0.469, "FG3M": 3, "FG3A": 10, "FG3_PCT": 0.3, "FTM": 16, "FTA": 20, "FT_PCT": 0.8, "OREB": 7, "DREB": 31, "REB": 38, "AST": 24, "STL": 3, "BLK": 4, "TOV": 7, "PF": 24, "PTS": 95}, {"Team_ID": 1610612750, "Game_ID": "0020300279", "GAME_DATE": "DEC 07, 2003", "MATCHUP": "MIN @ LAC", "WL": "W", "MIN": 240, "FGM": 40, "FGA": 83, "FG_PCT": 0.482, "FG3M": 2, "FG3A": 8, "FG3_PCT": 0.25, "FTM": 14, "FTA": 16, "FT_PCT": 0.875, "OREB": 8, "DREB": 22, "REB": 30, "AST": 26, "STL": 15, "BLK": 7, "TOV": 15, "PF": 24, "PTS": 96}, {"Team_ID": 1610612750, "Game_ID": "0020300269", "GAME_DATE": "DEC 05, 2003", "MATCHUP": "MIN @ SAC", "WL": "W", "MIN": 265, "FGM": 45, "FGA": 87, "FG_PCT": 0.517, "FG3M": 4, "FG3A": 10, "FG3_PCT": 0.4, "FTM": 18, "FTA": 22, "FT_PCT": 0.818, "OREB": 5, "DREB": 41, "REB": 46, "AST": 20, "STL": 6, "BLK": 5, "TOV": 12, "PF": 29, "PTS": 112}, {"Team_ID": 1610612750, "Game_ID": "0020300252", "GAME_DATE": "DEC 03, 2003", "MATCHUP": "MIN @ PHX", "WL": "W", "MIN": 240, "FGM": 38, "FGA": 80, "FG_PCT": 0.475, "FG3M": 7, "FG3A": 18, "FG3_PCT": 0.3888888888888889, "FTM": 9, "FTA": 15, "FT_PCT": 0.6, "OREB": 9, "DREB": 38, "REB": 47, "AST": 23, "STL": 6, "BLK": 9, "TOV": 13, "PF": 12, "PTS": 92}, {"Team_ID": 1610612750, "Game_ID": "0020300228", "GAME_DATE": "NOV 29, 2003", "MATCHUP": "MIN @ DAL", "WL": "L", "MIN": 240, "FGM": 38, "FGA": 86, "FG_PCT": 0.442, "FG3M": 3, "FG3A": 16, "FG3_PCT": 0.1875, "FTM": 9, "FTA": 12, "FT_PCT": 0.75, "OREB": 12, "DREB": 40, "REB": 52, "AST": 22, "STL": 6, "BLK": 9, "TOV": 16, "PF": 24, "PTS": 88}, {"Team_ID": 1610612750, "Game_ID": "0020300216", "GAME_DATE": "NOV 28, 2003", "MATCHUP": "MIN @ MEM", "WL": "W", "MIN": 240, "FGM": 37, "FGA": 75, "FG_PCT": 0.493, "FG3M": 2, "FG3A": 7, "FG3_PCT": 0.2857142857142857, "FTM": 26, "FTA": 32, "FT_PCT": 0.813, "OREB": 7, "DREB": 37, "REB": 44, "AST": 24, "STL": 7, "BLK": 8, "TOV": 14, "PF": 22, "PTS": 102}, {"Team_ID": 1610612750, "Game_ID": "0020300204", "GAME_DATE": "NOV 26, 2003", "MATCHUP": "MIN vs. NYK", "WL": "L", "MIN": 240, "FGM": 41, "FGA": 82, "FG_PCT": 0.5, "FG3M": 4, "FG3A": 12, "FG3_PCT": 0.3333333333333333, "FTM": 6, "FTA": 9, "FT_PCT": 0.667, "OREB": 5, "DREB": 29, "REB": 34, "AST": 29, "STL": 3, "BLK": 3, "TOV": 8, "PF": 21, "PTS": 92}, {"Team_ID": 1610612750, "Game_ID": "0020300192", "GAME_DATE": "NOV 25, 2003", "MATCHUP": "MIN @ IND", "WL": "L", "MIN": 240, "FGM": 28, "FGA": 72, "FG_PCT": 0.389, "FG3M": 2, "FG3A": 6, "FG3_PCT": 0.3333333333333333, "FTM": 17, "FTA": 22, "FT_PCT": 0.773, "OREB": 9, "DREB": 28, "REB": 37, "AST": 16, "STL": 3, "BLK": 10, "TOV": 12, "PF": 17, "PTS": 75}, {"Team_ID": 1610612750, "Game_ID": "0020300179", "GAME_DATE": "NOV 22, 2003", "MATCHUP": "MIN vs. LAC", "WL": "W", "MIN": 240, "FGM": 43, "FGA": 82, "FG_PCT": 0.524, "FG3M": 5, "FG3A": 15, "FG3_PCT": 0.3333333333333333, "FTM": 12, "FTA": 13, "FT_PCT": 0.923, "OREB": 6, "DREB": 29, "REB": 35, "AST": 30, "STL": 10, "BLK": 4, "TOV": 7, "PF": 17, "PTS": 103}, {"Team_ID": 1610612750, "Game_ID": "0020300166", "GAME_DATE": "NOV 21, 2003", "MATCHUP": "MIN @ CLE", "WL": "W", "MIN": 240, "FGM": 38, "FGA": 90, "FG_PCT": 0.422, "FG3M": 6, "FG3A": 13, "FG3_PCT": 0.46153846153846156, "FTM": 15, "FTA": 16, "FT_PCT": 0.938, "OREB": 15, "DREB": 26, "REB": 41, "AST": 19, "STL": 7, "BLK": 6, "TOV": 8, "PF": 19, "PTS": 97}, {"Team_ID": 1610612750, "Game_ID": "0020300148", "GAME_DATE": "NOV 18, 2003", "MATCHUP": "MIN vs. DEN", "WL": "W", "MIN": 240, "FGM": 36, "FGA": 78, "FG_PCT": 0.462, "FG3M": 0, "FG3A": 4, "FG3_PCT": 0.0, "FTM": 17, "FTA": 20, "FT_PCT": 0.85, "OREB": 10, "DREB": 37, "REB": 47, "AST": 27, "STL": 6, "BLK": 7, "TOV": 11, "PF": 21, "PTS": 89}, {"Team_ID": 1610612750, "Game_ID": "0020300120", "GAME_DATE": "NOV 14, 2003", "MATCHUP": "MIN vs. UTA", "WL": "L", "MIN": 240, "FGM": 29, "FGA": 74, "FG_PCT": 0.392, "FG3M": 5, "FG3A": 13, "FG3_PCT": 0.38461538461538464, "FTM": 14, "FTA": 19, "FT_PCT": 0.737, "OREB": 11, "DREB": 29, "REB": 40, "AST": 22, "STL": 11, "BLK": 7, "TOV": 20, "PF": 27, "PTS": 77}, {"Team_ID": 1610612750, "Game_ID": "0020300113", "GAME_DATE": "NOV 13, 2003", "MATCHUP": "MIN @ CHI", "WL": "W", "MIN": 265, "FGM": 38, "FGA": 84, "FG_PCT": 0.452, "FG3M": 4, "FG3A": 15, "FG3_PCT": 0.26666666666666666, "FTM": 12, "FTA": 17, "FT_PCT": 0.706, "OREB": 8, "DREB": 36, "REB": 44, "AST": 24, "STL": 9, "BLK": 3, "TOV": 16, "PF": 25, "PTS": 92}, {"Team_ID": 1610612750, "Game_ID": "0020300097", "GAME_DATE": "NOV 11, 2003", "MATCHUP": "MIN vs. SEA", "WL": "L", "MIN": 240, "FGM": 33, "FGA": 76, "FG_PCT": 0.434, "FG3M": 6, "FG3A": 12, "FG3_PCT": 0.5, "FTM": 15, "FTA": 21, "FT_PCT": 0.714, "OREB": 10, "DREB": 24, "REB": 34, "AST": 23, "STL": 8, "BLK": 6, "TOV": 15, "PF": 22, "PTS": 87}, {"Team_ID": 1610612750, "Game_ID": "0020300077", "GAME_DATE": "NOV 08, 2003", "MATCHUP": "MIN @ MIA", "WL": "W", "MIN": 240, "FGM": 33, "FGA": 72, "FG_PCT": 0.458, "FG3M": 5, "FG3A": 11, "FG3_PCT": 0.45454545454545453, "FTM": 17, "FTA": 21, "FT_PCT": 0.81, "OREB": 7, "DREB": 38, "REB": 45, "AST": 17, "STL": 1, "BLK": 7, "TOV": 15, "PF": 20, "PTS": 88}, {"Team_ID": 1610612750, "Game_ID": "0020300069", "GAME_DATE": "NOV 07, 2003", "MATCHUP": "MIN @ ORL", "WL": "W", "MIN": 240, "FGM": 41, "FGA": 90, "FG_PCT": 0.456, "FG3M": 5, "FG3A": 10, "FG3_PCT": 0.5, "FTM": 13, "FTA": 18, "FT_PCT": 0.722, "OREB": 14, "DREB": 36, "REB": 50, "AST": 23, "STL": 7, "BLK": 2, "TOV": 8, "PF": 24, "PTS": 100}, {"Team_ID": 1610612750, "Game_ID": "0020300058", "GAME_DATE": "NOV 05, 2003", "MATCHUP": "MIN vs. SAC", "WL": "L", "MIN": 265, "FGM": 52, "FGA": 101, "FG_PCT": 0.515, "FG3M": 4, "FG3A": 9, "FG3_PCT": 0.4444444444444444, "FTM": 13, "FTA": 18, "FT_PCT": 0.722, "OREB": 18, "DREB": 28, "REB": 46, "AST": 32, "STL": 10, "BLK": 8, "TOV": 11, "PF": 27, "PTS": 121}, {"Team_ID": 1610612750, "Game_ID": "0020300046", "GAME_DATE": "NOV 03, 2003", "MATCHUP": "MIN @ UTA", "WL": "L", "MIN": 240, "FGM": 36, "FGA": 81, "FG_PCT": 0.444, "FG3M": 6, "FG3A": 14, "FG3_PCT": 0.42857142857142855, "FTM": 10, "FTA": 12, "FT_PCT": 0.833, "OREB": 10, "DREB": 23, "REB": 33, "AST": 21, "STL": 8, "BLK": 6, "TOV": 9, "PF": 24, "PTS": 88}, {"Team_ID": 1610612750, "Game_ID": "0020300031", "GAME_DATE": "NOV 01, 2003", "MATCHUP": "MIN vs. TOR", "WL": "W", "MIN": 240, "FGM": 31, "FGA": 68, "FG_PCT": 0.456, "FG3M": 2, "FG3A": 5, "FG3_PCT": 0.4, "FTM": 9, "FTA": 11, "FT_PCT": 0.818, "OREB": 7, "DREB": 28, "REB": 35, "AST": 20, "STL": 5, "BLK": 10, "TOV": 11, "PF": 22, "PTS": 73}, {"Team_ID": 1610612750, "Game_ID": "0020300022", "GAME_DATE": "OCT 31, 2003", "MATCHUP": "MIN @ NJN", "WL": "L", "MIN": 240, "FGM": 25, "FGA": 75, "FG_PCT": 0.333, "FG3M": 2, "FG3A": 10, "FG3_PCT": 0.2, "FTM": 9, "FTA": 11, "FT_PCT": 0.818, "OREB": 11, "DREB": 25, "REB": 36, "AST": 15, "STL": 5, "BLK": 5, "TOV": 25, "PF": 22, "PTS": 61}, {"Team_ID": 1610612750, "Game_ID": "0020300009", "GAME_DATE": "OCT 29, 2003", "MATCHUP": "MIN vs. MIL", "WL": "W", "MIN": 240, "FGM": 38, "FGA": 85, "FG_PCT": 0.447, "FG3M": 1, "FG3A": 6, "FG3_PCT": 0.16666666666666666, "FTM": 18, "FTA": 28, "FT_PCT": 0.643, "OREB": 15, "DREB": 32, "REB": 47, "AST": 26, "STL": 8, "BLK": 5, "TOV": 8, "PF": 14, "PTS": 95}]